<markdown_skeleton_root>
  <block_element>
    <ArrayOfMarkdownBlockBase xmlns:xsi="http://www.w3.org/2001/XMLSchema-instance" xmlns:xsd="http://www.w3.org/2001/XMLSchema">
      <MarkdownBlockBase
        xsi:type="MarkdownHeaderBlock"
        item_id="44c78b59-dcae-4073-8e4b-4edce65be3d5"
        item_type="Header"
        item_footer="footer_not_set"
        trans_unit_id="44c78b59-dcae-4073-8e4b-4edce65be3d5">
        <segment
          trans_unit_id="101">
          <SegmentId>80a4609a-7277-47a0-a0b7-216dbb62e6fa</SegmentId>
          <InternalNormalItem
            internal_item_id="1"
            internal_item_parent_id="101"
            trans_unit_id="101-1"
            internal_item_type="Normal">
            <internal_items />
          </InternalNormalItem>
        </segment>
        <header_type>Star</header_type>
        <header_level>1</header_level>
      </MarkdownBlockBase>
      <MarkdownBlockBase
        xsi:type="MarkdownParagraphBlock"
        item_id="eae86bd5-7810-486a-b99b-476c79740787"
        item_type="NormalParagraph"
        item_footer=""
        trans_unit_id="eae86bd5-7810-486a-b99b-476c79740787">
        <Lines>
          <MarkdownLine>
            <LineId>985d666a-a1dd-456c-89d3-898bf5c50e6b</LineId>
            <paragraph_segments>
              <MarkdownSegment
                trans_unit_id="102">
                <SegmentId>1013ca1c-146c-4032-ae78-710d40f5aa2e</SegmentId>
                <InternalNormalItem
                  internal_item_id="1"
                  internal_item_parent_id="102"
                  trans_unit_id="102-1"
                  internal_item_type="Normal">
                  <internal_items />
                </InternalNormalItem>
              </MarkdownSegment>
            </paragraph_segments>
            <PrefixWSLength>0</PrefixWSLength>
            <SuffixWSLength>0</SuffixWSLength>
          </MarkdownLine>
        </Lines>
        <paragraph_segments>
          <MarkdownSegment
            trans_unit_id="102">
            <SegmentId>1013ca1c-146c-4032-ae78-710d40f5aa2e</SegmentId>
            <InternalNormalItem
              internal_item_id="1"
              internal_item_parent_id="102"
              trans_unit_id="102-1"
              internal_item_type="Normal">
              <internal_items />
            </InternalNormalItem>
          </MarkdownSegment>
        </paragraph_segments>
      </MarkdownBlockBase>
      <MarkdownBlockBase
        xsi:type="MarkdownHeaderBlock"
        item_id="67067433-946b-41e0-bdc8-4c231e4a10bc"
        item_type="Header"
        item_footer="footer_not_set"
        trans_unit_id="67067433-946b-41e0-bdc8-4c231e4a10bc">
        <segment
          trans_unit_id="103">
          <SegmentId>8627168b-ebaf-48db-8d50-83f43fa0bd65</SegmentId>
          <InternalNormalItem
            internal_item_id="1"
            internal_item_parent_id="103"
            trans_unit_id="103-1"
            internal_item_type="Normal">
            <internal_items />
          </InternalNormalItem>
        </segment>
        <header_type>Star</header_type>
        <header_level>3</header_level>
      </MarkdownBlockBase>
      <MarkdownBlockBase
        xsi:type="MarkdownListBlock"
        item_id="b1d5153d-54be-404d-99c2-119955789ba3"
        item_type="List"
        item_footer=""
        trans_unit_id="b1d5153d-54be-404d-99c2-119955789ba3">
        <inner_list_items>
          <ListItem>
            <MarkdownParagraphBlock
              item_id="977fa907-2e7b-49e2-bf18-2512a481ca34"
              item_type="NormalParagraph"
              item_footer="footer_not_set"
              trans_unit_id="977fa907-2e7b-49e2-bf18-2512a481ca34">
              <Lines>
                <MarkdownLine>
                  <LineId>e630fdb7-f1de-4225-a736-dea20bb5cd59</LineId>
                  <paragraph_segments>
                    <MarkdownSegment
                      trans_unit_id="104">
                      <SegmentId>19180fc8-bd04-4f6c-8bc1-c1eb192b1a01</SegmentId>
                      <InternalNormalItem
                        internal_item_id="1"
                        internal_item_parent_id="104"
                        trans_unit_id="104-1"
                        internal_item_type="Normal">
                        <internal_items />
                      </InternalNormalItem>
                      <MarkdownInternalBoldItem
                        internal_item_id="2"
                        internal_item_parent_id="104"
                        trans_unit_id="104-2"
                        internal_item_type="Bold">
                        <internal_items />
                        <internal_itatic_bold_item_type>Star</internal_itatic_bold_item_type>
                      </MarkdownInternalBoldItem>
                      <InternalNormalItem
                        internal_item_id="3"
                        internal_item_parent_id="104"
                        trans_unit_id="104-3"
                        internal_item_type="Normal">
                        <internal_items />
                      </InternalNormalItem>
                    </MarkdownSegment>
                  </paragraph_segments>
                  <PrefixWSLength>2</PrefixWSLength>
                  <SuffixWSLength>0</SuffixWSLength>
                </MarkdownLine>
              </Lines>
              <paragraph_segments>
                <MarkdownSegment
                  trans_unit_id="104">
                  <SegmentId>19180fc8-bd04-4f6c-8bc1-c1eb192b1a01</SegmentId>
                  <InternalNormalItem
                    internal_item_id="1"
                    internal_item_parent_id="104"
                    trans_unit_id="104-1"
                    internal_item_type="Normal">
                    <internal_items />
                  </InternalNormalItem>
                  <MarkdownInternalBoldItem
                    internal_item_id="2"
                    internal_item_parent_id="104"
                    trans_unit_id="104-2"
                    internal_item_type="Bold">
                    <internal_items />
                    <internal_itatic_bold_item_type>Star</internal_itatic_bold_item_type>
                  </MarkdownInternalBoldItem>
                  <InternalNormalItem
                    internal_item_id="3"
                    internal_item_parent_id="104"
                    trans_unit_id="104-3"
                    internal_item_type="Normal">
                    <internal_items />
                  </InternalNormalItem>
                </MarkdownSegment>
              </paragraph_segments>
            </MarkdownParagraphBlock>
            <Identifier>1.</Identifier>
            <IndentsLength>
              <int>0</int>
            </IndentsLength>
          </ListItem>
          <ListItem>
            <MarkdownParagraphBlock
              item_id="38912d12-ad97-4953-973c-9e1fed915cc8"
              item_type="NormalParagraph"
              item_footer="footer_not_set"
              trans_unit_id="38912d12-ad97-4953-973c-9e1fed915cc8">
              <Lines>
                <MarkdownLine>
                  <LineId>60e6c844-b8c3-4ebb-95ae-da79718c04b1</LineId>
                  <paragraph_segments>
                    <MarkdownSegment
                      trans_unit_id="105">
                      <SegmentId>a1a0f8b3-36ce-4bc1-80a4-41b858122141</SegmentId>
                      <InternalNormalItem
                        internal_item_id="1"
                        internal_item_parent_id="105"
                        trans_unit_id="105-1"
                        internal_item_type="Normal">
                        <internal_items />
                      </InternalNormalItem>
                    </MarkdownSegment>
                  </paragraph_segments>
                  <PrefixWSLength>2</PrefixWSLength>
                  <SuffixWSLength>0</SuffixWSLength>
                </MarkdownLine>
              </Lines>
              <paragraph_segments>
                <MarkdownSegment
                  trans_unit_id="105">
                  <SegmentId>a1a0f8b3-36ce-4bc1-80a4-41b858122141</SegmentId>
                  <InternalNormalItem
                    internal_item_id="1"
                    internal_item_parent_id="105"
                    trans_unit_id="105-1"
                    internal_item_type="Normal">
                    <internal_items />
                  </InternalNormalItem>
                </MarkdownSegment>
              </paragraph_segments>
            </MarkdownParagraphBlock>
            <Identifier>2.</Identifier>
            <IndentsLength>
              <int>0</int>
            </IndentsLength>
          </ListItem>
        </inner_list_items>
        <ListType>Number</ListType>
      </MarkdownBlockBase>
      <MarkdownBlockBase
        xsi:type="MarkdownFencedCodeBlock"
        item_id="d84f9501-33ac-488c-8950-e896beac8ada"
        item_type="FencedCodeBlock"
        item_footer="footer_not_set"
        trans_unit_id="d84f9501-33ac-488c-8950-e896beac8ada">
        <codeblock_wraper> ```</codeblock_wraper>
        <code_block>get-command –module hyper-v | out-gridview</code_block>
        <fenced_code_lang>powershell</fenced_code_lang>
      </MarkdownBlockBase>
      <MarkdownBlockBase
        xsi:type="MarkdownParagraphBlock"
        item_id="eab6dfeb-1dcc-4274-957c-4480e43743a1"
        item_type="NormalParagraph"
        item_footer=""
        trans_unit_id="eab6dfeb-1dcc-4274-957c-4480e43743a1">
        <Lines>
          <MarkdownLine>
            <LineId>e1eb3ca8-2739-4c67-893f-f7350b4ef1aa</LineId>
            <paragraph_segments>
              <MarkdownSegment
                trans_unit_id="106">
                <SegmentId>b0fe14c5-ca8b-42ec-80e4-54e0b72c0916</SegmentId>
                <InternalNormalItem
                  internal_item_id="1"
                  internal_item_parent_id="106"
                  trans_unit_id="106-1"
                  internal_item_type="Normal">
                  <internal_items />
                </InternalNormalItem>
              </MarkdownSegment>
            </paragraph_segments>
            <PrefixWSLength>2</PrefixWSLength>
            <SuffixWSLength>0</SuffixWSLength>
          </MarkdownLine>
        </Lines>
        <paragraph_segments>
          <MarkdownSegment
            trans_unit_id="106">
            <SegmentId>b0fe14c5-ca8b-42ec-80e4-54e0b72c0916</SegmentId>
            <InternalNormalItem
              internal_item_id="1"
              internal_item_parent_id="106"
              trans_unit_id="106-1"
              internal_item_type="Normal">
              <internal_items />
            </InternalNormalItem>
          </MarkdownSegment>
        </paragraph_segments>
      </MarkdownBlockBase>
      <MarkdownBlockBase
        xsi:type="MarkdownParagraphBlock"
        item_id="6a4964f2-75de-489f-9f3b-3f5c81154ead"
        item_type="NormalParagraph"
        item_footer=""
        trans_unit_id="6a4964f2-75de-489f-9f3b-3f5c81154ead">
        <Lines>
          <MarkdownLine>
            <LineId>787b4871-8cac-4271-8568-f7a2e4703537</LineId>
            <paragraph_segments>
              <MarkdownSegment
                trans_unit_id="107">
                <SegmentId>156d1bf7-2209-4b88-97f4-5928c8337162</SegmentId>
                <ImageItem
                  internal_item_id="1"
                  internal_item_parent_id="107"
                  trans_unit_id="107-1"
                  internal_item_type="Image">
                  <internal_items />
                  <internal_Image_type>Inline</internal_Image_type>
                  <internal_link_text />
                  <internal_link_url>media\command_grid.png</internal_link_url>
                  <internal_link_title />
                </ImageItem>
              </MarkdownSegment>
            </paragraph_segments>
            <PrefixWSLength>2</PrefixWSLength>
            <SuffixWSLength>0</SuffixWSLength>
          </MarkdownLine>
        </Lines>
        <paragraph_segments>
          <MarkdownSegment
            trans_unit_id="107">
            <SegmentId>156d1bf7-2209-4b88-97f4-5928c8337162</SegmentId>
            <ImageItem
              internal_item_id="1"
              internal_item_parent_id="107"
              trans_unit_id="107-1"
              internal_item_type="Image">
              <internal_items />
              <internal_Image_type>Inline</internal_Image_type>
              <internal_link_text />
              <internal_link_url>media\command_grid.png</internal_link_url>
              <internal_link_title />
            </ImageItem>
          </MarkdownSegment>
        </paragraph_segments>
      </MarkdownBlockBase>
      <MarkdownBlockBase
        xsi:type="MarkdownListBlock"
        item_id="d611b898-a690-4ca1-88ca-ba795c69bed4"
        item_type="List"
        item_footer=""
        trans_unit_id="d611b898-a690-4ca1-88ca-ba795c69bed4">
        <inner_list_items>
          <ListItem>
            <MarkdownParagraphBlock
              item_id="529a68a4-b5be-4733-9d83-4fdf35054bce"
              item_type="NormalParagraph"
              item_footer="footer_not_set"
              trans_unit_id="529a68a4-b5be-4733-9d83-4fdf35054bce">
              <Lines>
                <MarkdownLine>
                  <LineId>f2429511-b983-4baa-86be-591324f9a54e</LineId>
                  <paragraph_segments>
                    <MarkdownSegment
                      trans_unit_id="108">
                      <SegmentId>558a3ba6-447d-4303-823a-fc0b59c46a48</SegmentId>
                      <InternalNormalItem
                        internal_item_id="1"
                        internal_item_parent_id="108"
                        trans_unit_id="108-1"
                        internal_item_type="Normal">
                        <internal_items />
                      </InternalNormalItem>
                      <CodeSpanItem
                        internal_item_id="2"
                        internal_item_parent_id="108"
                        trans_unit_id="108-2"
                        internal_item_type="CodeSpan">
                        <internal_items />
                        <ItemValue>get-help</ItemValue>
                      </CodeSpanItem>
                      <InternalNormalItem
                        internal_item_id="3"
                        internal_item_parent_id="108"
                        trans_unit_id="108-3"
                        internal_item_type="Normal">
                        <internal_items />
                      </InternalNormalItem>
                    </MarkdownSegment>
                    <MarkdownSegment
                      trans_unit_id="109">
                      <SegmentId>dc54fe76-61d2-4ed8-a3d6-2e7180d9dc82</SegmentId>
                      <InternalNormalItem
                        internal_item_id="1"
                        internal_item_parent_id="109"
                        trans_unit_id="109-1"
                        internal_item_type="Normal">
                        <internal_items />
                      </InternalNormalItem>
                      <CodeSpanItem
                        internal_item_id="2"
                        internal_item_parent_id="109"
                        trans_unit_id="109-2"
                        internal_item_type="CodeSpan">
                        <internal_items />
                        <ItemValue>get-vm</ItemValue>
                      </CodeSpanItem>
                      <InternalNormalItem
                        internal_item_id="3"
                        internal_item_parent_id="109"
                        trans_unit_id="109-3"
                        internal_item_type="Normal">
                        <internal_items />
                      </InternalNormalItem>
                    </MarkdownSegment>
                  </paragraph_segments>
                  <PrefixWSLength>1</PrefixWSLength>
                  <SuffixWSLength>0</SuffixWSLength>
                </MarkdownLine>
              </Lines>
              <paragraph_segments>
                <MarkdownSegment
                  trans_unit_id="108">
                  <SegmentId>558a3ba6-447d-4303-823a-fc0b59c46a48</SegmentId>
                  <InternalNormalItem
                    internal_item_id="1"
                    internal_item_parent_id="108"
                    trans_unit_id="108-1"
                    internal_item_type="Normal">
                    <internal_items />
                  </InternalNormalItem>
                  <CodeSpanItem
                    internal_item_id="2"
                    internal_item_parent_id="108"
                    trans_unit_id="108-2"
                    internal_item_type="CodeSpan">
                    <internal_items />
                    <ItemValue>get-help</ItemValue>
                  </CodeSpanItem>
                  <InternalNormalItem
                    internal_item_id="3"
                    internal_item_parent_id="108"
                    trans_unit_id="108-3"
                    internal_item_type="Normal">
                    <internal_items />
                  </InternalNormalItem>
                </MarkdownSegment>
                <MarkdownSegment
                  trans_unit_id="109">
                  <SegmentId>dc54fe76-61d2-4ed8-a3d6-2e7180d9dc82</SegmentId>
                  <InternalNormalItem
                    internal_item_id="1"
                    internal_item_parent_id="109"
                    trans_unit_id="109-1"
                    internal_item_type="Normal">
                    <internal_items />
                  </InternalNormalItem>
                  <CodeSpanItem
                    internal_item_id="2"
                    internal_item_parent_id="109"
                    trans_unit_id="109-2"
                    internal_item_type="CodeSpan">
                    <internal_items />
                    <ItemValue>get-vm</ItemValue>
                  </CodeSpanItem>
                  <InternalNormalItem
                    internal_item_id="3"
                    internal_item_parent_id="109"
                    trans_unit_id="109-3"
                    internal_item_type="Normal">
                    <internal_items />
                  </InternalNormalItem>
                </MarkdownSegment>
              </paragraph_segments>
            </MarkdownParagraphBlock>
            <Identifier>3.</Identifier>
            <IndentsLength>
              <int>0</int>
            </IndentsLength>
          </ListItem>
        </inner_list_items>
        <ListType>Number</ListType>
      </MarkdownBlockBase>
      <MarkdownBlockBase
        xsi:type="MarkdownFencedCodeBlock"
        item_id="4db608f2-d013-48c0-a81f-4d9b3a80ac01"
        item_type="FencedCodeBlock"
        item_footer="footer_not_set"
        trans_unit_id="4db608f2-d013-48c0-a81f-4d9b3a80ac01">
        <codeblock_wraper>  ```</codeblock_wraper>
        <code_block>get-help get-vm</code_block>
        <fenced_code_lang>powershell</fenced_code_lang>
      </MarkdownBlockBase>
      <MarkdownBlockBase
        xsi:type="MarkdownParagraphBlock"
        item_id="9e17b74d-842f-4b03-a199-0113bd69d381"
        item_type="NormalParagraph"
        item_footer=""
        trans_unit_id="9e17b74d-842f-4b03-a199-0113bd69d381">
        <Lines>
          <MarkdownLine>
            <LineId>8c6e8e82-5b97-428c-bfe3-1940b044d1d1</LineId>
            <paragraph_segments>
              <MarkdownSegment
                trans_unit_id="110">
                <SegmentId>0261692d-d1c2-43fd-a551-6eb4f6153a8a</SegmentId>
                <InternalNormalItem
                  internal_item_id="1"
                  internal_item_parent_id="110"
                  trans_unit_id="110-1"
                  internal_item_type="Normal">
                  <internal_items />
                </InternalNormalItem>
              </MarkdownSegment>
            </paragraph_segments>
            <PrefixWSLength>1</PrefixWSLength>
            <SuffixWSLength>0</SuffixWSLength>
          </MarkdownLine>
        </Lines>
        <paragraph_segments>
          <MarkdownSegment
            trans_unit_id="110">
            <SegmentId>0261692d-d1c2-43fd-a551-6eb4f6153a8a</SegmentId>
            <InternalNormalItem
              internal_item_id="1"
              internal_item_parent_id="110"
              trans_unit_id="110-1"
              internal_item_type="Normal">
              <internal_items />
            </InternalNormalItem>
          </MarkdownSegment>
        </paragraph_segments>
      </MarkdownBlockBase>
      <MarkdownBlockBase
        xsi:type="MarkdownParagraphBlock"
        item_id="d2eba48f-d0f8-4d11-a723-febfe6f5fa39"
        item_type="NormalParagraph"
        item_footer="&#xA;"
        trans_unit_id="d2eba48f-d0f8-4d11-a723-febfe6f5fa39">
        <Lines>
          <MarkdownLine>
            <LineId>8545dbe5-6a19-4b3e-a36f-0e2628ffac79</LineId>
            <paragraph_segments>
              <MarkdownSegment
                trans_unit_id="111">
                <SegmentId>08eb2dab-7dec-4612-97e7-d9def11ae49d</SegmentId>
                <ImageItem
                  internal_item_id="1"
                  internal_item_parent_id="111"
                  trans_unit_id="111-1"
                  internal_item_type="Image">
                  <internal_items />
                  <internal_Image_type>Inline</internal_Image_type>
                  <internal_link_text />
                  <internal_link_url>media\get_help.png</internal_link_url>
                  <internal_link_title />
                </ImageItem>
              </MarkdownSegment>
            </paragraph_segments>
            <PrefixWSLength>1</PrefixWSLength>
            <SuffixWSLength>0</SuffixWSLength>
          </MarkdownLine>
        </Lines>
        <paragraph_segments>
          <MarkdownSegment
            trans_unit_id="111">
            <SegmentId>08eb2dab-7dec-4612-97e7-d9def11ae49d</SegmentId>
            <ImageItem
              internal_item_id="1"
              internal_item_parent_id="111"
              trans_unit_id="111-1"
              internal_item_type="Image">
              <internal_items />
              <internal_Image_type>Inline</internal_Image_type>
              <internal_link_text />
              <internal_link_url>media\get_help.png</internal_link_url>
              <internal_link_title />
            </ImageItem>
          </MarkdownSegment>
        </paragraph_segments>
      </MarkdownBlockBase>
      <MarkdownBlockBase
        xsi:type="MarkdownHeaderBlock"
        item_id="6d8ba198-ceff-4a3b-8808-90c27db1e0cc"
        item_type="Header"
        item_footer="footer_not_set"
        trans_unit_id="6d8ba198-ceff-4a3b-8808-90c27db1e0cc">
        <segment
          trans_unit_id="112">
          <SegmentId>fbd23e8c-6b49-4626-b613-4acceeddd961</SegmentId>
          <InternalNormalItem
            internal_item_id="1"
            internal_item_parent_id="112"
            trans_unit_id="112-1"
            internal_item_type="Normal">
            <internal_items />
          </InternalNormalItem>
        </segment>
        <header_type>Star</header_type>
        <header_level>3</header_level>
      </MarkdownBlockBase>
      <MarkdownBlockBase
        xsi:type="MarkdownParagraphBlock"
        item_id="0e38f36c-16f5-4f0d-9edd-a0513e2f6355"
        item_type="NormalParagraph"
        item_footer=""
        trans_unit_id="0e38f36c-16f5-4f0d-9edd-a0513e2f6355">
        <Lines>
          <MarkdownLine>
            <LineId>9cbb7ed9-31b8-4840-8779-8dbe02c67e53</LineId>
            <paragraph_segments>
              <MarkdownSegment
                trans_unit_id="113">
                <SegmentId>52d26f10-d583-4e91-97b0-719bc3828e5e</SegmentId>
                <InternalNormalItem
                  internal_item_id="1"
                  internal_item_parent_id="113"
                  trans_unit_id="113-1"
                  internal_item_type="Normal">
                  <internal_items />
                </InternalNormalItem>
                <CodeSpanItem
                  internal_item_id="2"
                  internal_item_parent_id="113"
                  trans_unit_id="113-2"
                  internal_item_type="CodeSpan">
                  <internal_items />
                  <ItemValue>get-vm</ItemValue>
                </CodeSpanItem>
                <InternalNormalItem
                  internal_item_id="3"
                  internal_item_parent_id="113"
                  trans_unit_id="113-3"
                  internal_item_type="Normal">
                  <internal_items />
                </InternalNormalItem>
              </MarkdownSegment>
            </paragraph_segments>
            <PrefixWSLength>0</PrefixWSLength>
            <SuffixWSLength>0</SuffixWSLength>
          </MarkdownLine>
        </Lines>
        <paragraph_segments>
          <MarkdownSegment
            trans_unit_id="113">
            <SegmentId>52d26f10-d583-4e91-97b0-719bc3828e5e</SegmentId>
            <InternalNormalItem
              internal_item_id="1"
              internal_item_parent_id="113"
              trans_unit_id="113-1"
              internal_item_type="Normal">
              <internal_items />
            </InternalNormalItem>
            <CodeSpanItem
              internal_item_id="2"
              internal_item_parent_id="113"
              trans_unit_id="113-2"
              internal_item_type="CodeSpan">
              <internal_items />
              <ItemValue>get-vm</ItemValue>
            </CodeSpanItem>
            <InternalNormalItem
              internal_item_id="3"
              internal_item_parent_id="113"
              trans_unit_id="113-3"
              internal_item_type="Normal">
              <internal_items />
            </InternalNormalItem>
          </MarkdownSegment>
        </paragraph_segments>
      </MarkdownBlockBase>
      <MarkdownBlockBase
        xsi:type="MarkdownListBlock"
        item_id="3287871f-a2c2-4fae-becd-08320d2afa79"
        item_type="List"
        item_footer=""
        trans_unit_id="3287871f-a2c2-4fae-becd-08320d2afa79">
        <inner_list_items>
          <ListItem>
            <MarkdownParagraphBlock
              item_id="3a4159c9-6762-4891-ab6c-72609b49c7c6"
              item_type="NormalParagraph"
              item_footer="footer_not_set"
              trans_unit_id="3a4159c9-6762-4891-ab6c-72609b49c7c6">
              <Lines>
                <MarkdownLine>
                  <LineId>639969ec-e661-470c-a822-29eaf59c9704</LineId>
                  <paragraph_segments>
                    <MarkdownSegment
                      trans_unit_id="114">
                      <SegmentId>98f8bc5b-e405-4a7e-8295-a1f9b8917747</SegmentId>
                      <InternalNormalItem
                        internal_item_id="1"
                        internal_item_parent_id="114"
                        trans_unit_id="114-1"
                        internal_item_type="Normal">
                        <internal_items />
                      </InternalNormalItem>
                    </MarkdownSegment>
                  </paragraph_segments>
                  <PrefixWSLength>1</PrefixWSLength>
                  <SuffixWSLength>0</SuffixWSLength>
                </MarkdownLine>
              </Lines>
              <paragraph_segments>
                <MarkdownSegment
                  trans_unit_id="114">
                  <SegmentId>98f8bc5b-e405-4a7e-8295-a1f9b8917747</SegmentId>
                  <InternalNormalItem
                    internal_item_id="1"
                    internal_item_parent_id="114"
                    trans_unit_id="114-1"
                    internal_item_type="Normal">
                    <internal_items />
                  </InternalNormalItem>
                </MarkdownSegment>
              </paragraph_segments>
            </MarkdownParagraphBlock>
            <Identifier>1.</Identifier>
            <IndentsLength>
              <int>0</int>
            </IndentsLength>
          </ListItem>
        </inner_list_items>
        <ListType>Number</ListType>
      </MarkdownBlockBase>
      <MarkdownBlockBase
        xsi:type="MarkdownFencedCodeBlock"
        item_id="812c2443-db0a-4f59-8bd0-841b0f9dba90"
        item_type="FencedCodeBlock"
        item_footer="footer_not_set"
        trans_unit_id="812c2443-db0a-4f59-8bd0-841b0f9dba90">
        <codeblock_wraper> ```</codeblock_wraper>
        <code_block>get-vm</code_block>
        <fenced_code_lang>powershell</fenced_code_lang>
      </MarkdownBlockBase>
      <MarkdownBlockBase
        xsi:type="MarkdownParagraphBlock"
        item_id="72c8f36f-f37f-4b04-b4de-14312fc81596"
        item_type="NormalParagraph"
        item_footer=""
        trans_unit_id="72c8f36f-f37f-4b04-b4de-14312fc81596">
        <Lines>
          <MarkdownLine>
            <LineId>39366607-1ee5-4ae3-b3ac-934dcdbfce11</LineId>
            <paragraph_segments>
              <MarkdownSegment
                trans_unit_id="115">
                <SegmentId>efedb76a-c473-4835-ab5a-230ff8569bac</SegmentId>
                <InternalNormalItem
                  internal_item_id="1"
                  internal_item_parent_id="115"
                  trans_unit_id="115-1"
                  internal_item_type="Normal">
                  <internal_items />
                </InternalNormalItem>
              </MarkdownSegment>
            </paragraph_segments>
            <PrefixWSLength>1</PrefixWSLength>
            <SuffixWSLength>0</SuffixWSLength>
          </MarkdownLine>
        </Lines>
        <paragraph_segments>
          <MarkdownSegment
            trans_unit_id="115">
            <SegmentId>efedb76a-c473-4835-ab5a-230ff8569bac</SegmentId>
            <InternalNormalItem
              internal_item_id="1"
              internal_item_parent_id="115"
              trans_unit_id="115-1"
              internal_item_type="Normal">
              <internal_items />
            </InternalNormalItem>
          </MarkdownSegment>
        </paragraph_segments>
      </MarkdownBlockBase>
      <MarkdownBlockBase
        xsi:type="MarkdownParagraphBlock"
        item_id="18779d62-4c56-4306-9d75-9fc80f498ab6"
        item_type="NormalParagraph"
        item_footer=""
        trans_unit_id="18779d62-4c56-4306-9d75-9fc80f498ab6">
        <Lines>
          <MarkdownLine>
            <LineId>4f2f0de5-59bb-4dd6-a132-dfc6180403e1</LineId>
            <paragraph_segments>
              <MarkdownSegment
                trans_unit_id="116">
                <SegmentId>eea1b39d-620e-4bc8-80c0-caf3de0001f1</SegmentId>
                <ImageItem
                  internal_item_id="1"
                  internal_item_parent_id="116"
                  trans_unit_id="116-1"
                  internal_item_type="Image">
                  <internal_items />
                  <internal_Image_type>Inline</internal_Image_type>
                  <internal_link_text />
                  <internal_link_url>media\get_vm.png</internal_link_url>
                  <internal_link_title />
                </ImageItem>
              </MarkdownSegment>
            </paragraph_segments>
            <PrefixWSLength>1</PrefixWSLength>
            <SuffixWSLength>0</SuffixWSLength>
          </MarkdownLine>
        </Lines>
        <paragraph_segments>
          <MarkdownSegment
            trans_unit_id="116">
            <SegmentId>eea1b39d-620e-4bc8-80c0-caf3de0001f1</SegmentId>
            <ImageItem
              internal_item_id="1"
              internal_item_parent_id="116"
              trans_unit_id="116-1"
              internal_item_type="Image">
              <internal_items />
              <internal_Image_type>Inline</internal_Image_type>
              <internal_link_text />
              <internal_link_url>media\get_vm.png</internal_link_url>
              <internal_link_title />
            </ImageItem>
          </MarkdownSegment>
        </paragraph_segments>
      </MarkdownBlockBase>
      <MarkdownBlockBase
        xsi:type="MarkdownListBlock"
        item_id="0e45dca5-204d-4e64-9e97-3270c6285e24"
        item_type="List"
        item_footer=""
        trans_unit_id="0e45dca5-204d-4e64-9e97-3270c6285e24">
        <inner_list_items>
          <ListItem>
            <MarkdownParagraphBlock
              item_id="a68ae02b-373f-405f-920b-2bf00f8e4628"
              item_type="NormalParagraph"
              item_footer="footer_not_set"
              trans_unit_id="a68ae02b-373f-405f-920b-2bf00f8e4628">
              <Lines>
                <MarkdownLine>
                  <LineId>4e84a04d-7c7e-4cfe-84ec-92f664a5f96a</LineId>
                  <paragraph_segments>
                    <MarkdownSegment
                      trans_unit_id="117">
                      <SegmentId>60357587-e704-4103-8b0f-112bdbdb2394</SegmentId>
                      <InternalNormalItem
                        internal_item_id="1"
                        internal_item_parent_id="117"
                        trans_unit_id="117-1"
                        internal_item_type="Normal">
                        <internal_items />
                      </InternalNormalItem>
                      <CodeSpanItem
                        internal_item_id="2"
                        internal_item_parent_id="117"
                        trans_unit_id="117-2"
                        internal_item_type="CodeSpan">
                        <internal_items />
                        <ItemValue>get-vm</ItemValue>
                      </CodeSpanItem>
                      <InternalNormalItem
                        internal_item_id="3"
                        internal_item_parent_id="117"
                        trans_unit_id="117-3"
                        internal_item_type="Normal">
                        <internal_items />
                      </InternalNormalItem>
                    </MarkdownSegment>
                    <MarkdownSegment
                      trans_unit_id="118">
                      <SegmentId>3574e814-4cf2-401b-9087-42b123edcfc7</SegmentId>
                      <InternalNormalItem
                        internal_item_id="1"
                        internal_item_parent_id="118"
                        trans_unit_id="118-1"
                        internal_item_type="Normal">
                        <internal_items />
                      </InternalNormalItem>
                    </MarkdownSegment>
                    <MarkdownSegment
                      trans_unit_id="119">
                      <SegmentId>35e72aee-9baa-4215-af07-89d22f9f67a5</SegmentId>
                      <InternalNormalItem
                        internal_item_id="1"
                        internal_item_parent_id="119"
                        trans_unit_id="119-1"
                        internal_item_type="Normal">
                        <internal_items />
                      </InternalNormalItem>
                      <LinkItem
                        internal_item_id="2"
                        internal_item_parent_id="119"
                        trans_unit_id="119-2"
                        internal_item_type="Link">
                        <internal_items />
                        <internal_link_type>Inline</internal_link_type>
                        <internal_link_text>Using the Where-Object</internal_link_text>
                        <internal_link_url>https://technet.microsoft.com/en-us/library/ee177028.aspx</internal_link_url>
                        <internal_link_title />
                      </LinkItem>
                      <InternalNormalItem
                        internal_item_id="3"
                        internal_item_parent_id="119"
                        trans_unit_id="119-3"
                        internal_item_type="Normal">
                        <internal_items />
                      </InternalNormalItem>
                    </MarkdownSegment>
                  </paragraph_segments>
                  <PrefixWSLength>1</PrefixWSLength>
                  <SuffixWSLength>0</SuffixWSLength>
                </MarkdownLine>
              </Lines>
              <paragraph_segments>
                <MarkdownSegment
                  trans_unit_id="117">
                  <SegmentId>60357587-e704-4103-8b0f-112bdbdb2394</SegmentId>
                  <InternalNormalItem
                    internal_item_id="1"
                    internal_item_parent_id="117"
                    trans_unit_id="117-1"
                    internal_item_type="Normal">
                    <internal_items />
                  </InternalNormalItem>
                  <CodeSpanItem
                    internal_item_id="2"
                    internal_item_parent_id="117"
                    trans_unit_id="117-2"
                    internal_item_type="CodeSpan">
                    <internal_items />
                    <ItemValue>get-vm</ItemValue>
                  </CodeSpanItem>
                  <InternalNormalItem
                    internal_item_id="3"
                    internal_item_parent_id="117"
                    trans_unit_id="117-3"
                    internal_item_type="Normal">
                    <internal_items />
                  </InternalNormalItem>
                </MarkdownSegment>
                <MarkdownSegment
                  trans_unit_id="118">
                  <SegmentId>3574e814-4cf2-401b-9087-42b123edcfc7</SegmentId>
                  <InternalNormalItem
                    internal_item_id="1"
                    internal_item_parent_id="118"
                    trans_unit_id="118-1"
                    internal_item_type="Normal">
                    <internal_items />
                  </InternalNormalItem>
                </MarkdownSegment>
                <MarkdownSegment
                  trans_unit_id="119">
                  <SegmentId>35e72aee-9baa-4215-af07-89d22f9f67a5</SegmentId>
                  <InternalNormalItem
                    internal_item_id="1"
                    internal_item_parent_id="119"
                    trans_unit_id="119-1"
                    internal_item_type="Normal">
                    <internal_items />
                  </InternalNormalItem>
                  <LinkItem
                    internal_item_id="2"
                    internal_item_parent_id="119"
                    trans_unit_id="119-2"
                    internal_item_type="Link">
                    <internal_items />
                    <internal_link_type>Inline</internal_link_type>
                    <internal_link_text>Using the Where-Object</internal_link_text>
                    <internal_link_url>https://technet.microsoft.com/en-us/library/ee177028.aspx</internal_link_url>
                    <internal_link_title />
                  </LinkItem>
                  <InternalNormalItem
                    internal_item_id="3"
                    internal_item_parent_id="119"
                    trans_unit_id="119-3"
                    internal_item_type="Normal">
                    <internal_items />
                  </InternalNormalItem>
                </MarkdownSegment>
              </paragraph_segments>
            </MarkdownParagraphBlock>
            <Identifier>2.</Identifier>
            <IndentsLength>
              <int>0</int>
            </IndentsLength>
          </ListItem>
        </inner_list_items>
        <ListType>Number</ListType>
      </MarkdownBlockBase>
      <MarkdownBlockBase
        xsi:type="MarkdownFencedCodeBlock"
        item_id="387243c5-2af1-4480-863f-3ab29410bfc7"
        item_type="FencedCodeBlock"
        item_footer="footer_not_set"
        trans_unit_id="387243c5-2af1-4480-863f-3ab29410bfc7">
        <codeblock_wraper> ```</codeblock_wraper>
        <code_block> get-vm | where {$_.State –eq ‘Running’}</code_block>
        <fenced_code_lang>powershell</fenced_code_lang>
      </MarkdownBlockBase>
      <MarkdownBlockBase
        xsi:type="MarkdownListBlock"
        item_id="b4caed4e-0525-4aac-ada6-793f57f9ef13"
        item_type="List"
        item_footer=""
        trans_unit_id="b4caed4e-0525-4aac-ada6-793f57f9ef13">
        <inner_list_items>
          <ListItem>
            <MarkdownParagraphBlock
              item_id="3742f655-ece6-4ad8-9430-3cd94f30359a"
              item_type="NormalParagraph"
              item_footer="footer_not_set"
              trans_unit_id="3742f655-ece6-4ad8-9430-3cd94f30359a">
              <Lines>
                <MarkdownLine>
                  <LineId>4c50d4ce-3e52-40dc-afc9-c9ea88767fd8</LineId>
                  <paragraph_segments>
                    <MarkdownSegment
                      trans_unit_id="120">
                      <SegmentId>4bcf7ddf-0086-47d3-b1fc-a73c3dfaf1e0</SegmentId>
                      <InternalNormalItem
                        internal_item_id="1"
                        internal_item_parent_id="120"
                        trans_unit_id="120-1"
                        internal_item_type="Normal">
                        <internal_items />
                      </InternalNormalItem>
                    </MarkdownSegment>
                    <MarkdownSegment
                      trans_unit_id="121">
                      <SegmentId>f45208a0-0cd3-425a-b34c-4763de6f3c2a</SegmentId>
                      <InternalNormalItem
                        internal_item_id="1"
                        internal_item_parent_id="121"
                        trans_unit_id="121-1"
                        internal_item_type="Normal">
                        <internal_items />
                      </InternalNormalItem>
                    </MarkdownSegment>
                  </paragraph_segments>
                  <PrefixWSLength>2</PrefixWSLength>
                  <SuffixWSLength>0</SuffixWSLength>
                </MarkdownLine>
              </Lines>
              <paragraph_segments>
                <MarkdownSegment
                  trans_unit_id="120">
                  <SegmentId>4bcf7ddf-0086-47d3-b1fc-a73c3dfaf1e0</SegmentId>
                  <InternalNormalItem
                    internal_item_id="1"
                    internal_item_parent_id="120"
                    trans_unit_id="120-1"
                    internal_item_type="Normal">
                    <internal_items />
                  </InternalNormalItem>
                </MarkdownSegment>
                <MarkdownSegment
                  trans_unit_id="121">
                  <SegmentId>f45208a0-0cd3-425a-b34c-4763de6f3c2a</SegmentId>
                  <InternalNormalItem
                    internal_item_id="1"
                    internal_item_parent_id="121"
                    trans_unit_id="121-1"
                    internal_item_type="Normal">
                    <internal_items />
                  </InternalNormalItem>
                </MarkdownSegment>
              </paragraph_segments>
            </MarkdownParagraphBlock>
            <Identifier>3.</Identifier>
            <IndentsLength>
              <int>0</int>
            </IndentsLength>
          </ListItem>
        </inner_list_items>
        <ListType>Number</ListType>
      </MarkdownBlockBase>
      <MarkdownBlockBase
        xsi:type="MarkdownFencedCodeBlock"
        item_id="5850285c-dde3-41fe-98a6-62100bc3d37d"
        item_type="FencedCodeBlock"
        item_footer=""
        trans_unit_id="5850285c-dde3-41fe-98a6-62100bc3d37d">
        <codeblock_wraper> ```</codeblock_wraper>
        <code_block> get-vm | where {$_.State –eq ‘Off’}</code_block>
        <fenced_code_lang>powershell</fenced_code_lang>
      </MarkdownBlockBase>
      <MarkdownBlockBase
        xsi:type="MarkdownHeaderBlock"
        item_id="91036590-55f0-4f7d-a6f4-fb76dcdeac61"
        item_type="Header"
        item_footer="footer_not_set"
        trans_unit_id="91036590-55f0-4f7d-a6f4-fb76dcdeac61">
        <segment
          trans_unit_id="122">
          <SegmentId>3ce56a42-1ec1-4372-84c9-485e54053387</SegmentId>
          <InternalNormalItem
            internal_item_id="1"
            internal_item_parent_id="122"
            trans_unit_id="122-1"
            internal_item_type="Normal">
            <internal_items />
          </InternalNormalItem>
        </segment>
        <header_type>Star</header_type>
        <header_level>3</header_level>
      </MarkdownBlockBase>
      <MarkdownBlockBase
        xsi:type="MarkdownListBlock"
        item_id="d6fb4f73-5f94-44be-9e49-e109ba244387"
        item_type="List"
        item_footer=""
        trans_unit_id="d6fb4f73-5f94-44be-9e49-e109ba244387">
        <inner_list_items>
          <ListItem>
            <MarkdownParagraphBlock
              item_id="06562e17-8cf8-4a48-b4fa-ab81b700827f"
              item_type="NormalParagraph"
              item_footer="footer_not_set"
              trans_unit_id="06562e17-8cf8-4a48-b4fa-ab81b700827f">
              <Lines>
                <MarkdownLine>
                  <LineId>6e23125e-15b4-4e0c-a973-9421b07df4ad</LineId>
                  <paragraph_segments>
                    <MarkdownSegment
                      trans_unit_id="123">
                      <SegmentId>3841f08c-1dbc-40f1-add8-e3c625f77390</SegmentId>
                      <InternalNormalItem
                        internal_item_id="1"
                        internal_item_parent_id="123"
                        trans_unit_id="123-1"
                        internal_item_type="Normal">
                        <internal_items />
                      </InternalNormalItem>
                    </MarkdownSegment>
                  </paragraph_segments>
                  <PrefixWSLength>1</PrefixWSLength>
                  <SuffixWSLength>0</SuffixWSLength>
                </MarkdownLine>
              </Lines>
              <paragraph_segments>
                <MarkdownSegment
                  trans_unit_id="123">
                  <SegmentId>3841f08c-1dbc-40f1-add8-e3c625f77390</SegmentId>
                  <InternalNormalItem
                    internal_item_id="1"
                    internal_item_parent_id="123"
                    trans_unit_id="123-1"
                    internal_item_type="Normal">
                    <internal_items />
                  </InternalNormalItem>
                </MarkdownSegment>
              </paragraph_segments>
            </MarkdownParagraphBlock>
            <Identifier>1.</Identifier>
            <IndentsLength>
              <int>0</int>
            </IndentsLength>
          </ListItem>
        </inner_list_items>
        <ListType>Number</ListType>
      </MarkdownBlockBase>
      <MarkdownBlockBase
        xsi:type="MarkdownFencedCodeBlock"
        item_id="51cd9ef1-2158-4bc0-9ca3-2d4b037aeaa4"
        item_type="FencedCodeBlock"
        item_footer=""
        trans_unit_id="51cd9ef1-2158-4bc0-9ca3-2d4b037aeaa4">
        <codeblock_wraper> ```</codeblock_wraper>
        <code_block> Start-vm –Name virtual machine name</code_block>
        <fenced_code_lang>powershell</fenced_code_lang>
      </MarkdownBlockBase>
      <MarkdownBlockBase
        xsi:type="MarkdownListBlock"
        item_id="1a9c4b48-c78c-4e8e-bff7-eea025a89ccc"
        item_type="List"
        item_footer=""
        trans_unit_id="1a9c4b48-c78c-4e8e-bff7-eea025a89ccc">
        <inner_list_items>
          <ListItem>
            <MarkdownParagraphBlock
              item_id="8eccded4-d792-4b64-89fe-576e6695ef42"
              item_type="NormalParagraph"
              item_footer="footer_not_set"
              trans_unit_id="8eccded4-d792-4b64-89fe-576e6695ef42">
              <Lines>
                <MarkdownLine>
                  <LineId>b5c54f9e-fff0-4112-8470-3ec212d02e29</LineId>
                  <paragraph_segments>
                    <MarkdownSegment
                      trans_unit_id="124">
                      <SegmentId>eb947a47-5955-462e-b7b1-81ae66a5b45b</SegmentId>
                      <InternalNormalItem
                        internal_item_id="1"
                        internal_item_parent_id="124"
                        trans_unit_id="124-1"
                        internal_item_type="Normal">
                        <internal_items />
                      </InternalNormalItem>
                    </MarkdownSegment>
                  </paragraph_segments>
                  <PrefixWSLength>1</PrefixWSLength>
                  <SuffixWSLength>0</SuffixWSLength>
                </MarkdownLine>
              </Lines>
              <paragraph_segments>
                <MarkdownSegment
                  trans_unit_id="124">
                  <SegmentId>eb947a47-5955-462e-b7b1-81ae66a5b45b</SegmentId>
                  <InternalNormalItem
                    internal_item_id="1"
                    internal_item_parent_id="124"
                    trans_unit_id="124-1"
                    internal_item_type="Normal">
                    <internal_items />
                  </InternalNormalItem>
                </MarkdownSegment>
              </paragraph_segments>
            </MarkdownParagraphBlock>
            <Identifier>2.</Identifier>
            <IndentsLength>
              <int>0</int>
            </IndentsLength>
          </ListItem>
        </inner_list_items>
        <ListType>Number</ListType>
      </MarkdownBlockBase>
      <MarkdownBlockBase
        xsi:type="MarkdownFencedCodeBlock"
        item_id="72798be8-4adc-4603-a1c8-2c2e2b79d0c0"
        item_type="FencedCodeBlock"
        item_footer="footer_not_set"
        trans_unit_id="72798be8-4adc-4603-a1c8-2c2e2b79d0c0">
        <codeblock_wraper>  ```</codeblock_wraper>
        <code_block> get-vm | where {$_.State –eq ‘Off’} | start-vm</code_block>
        <fenced_code_lang>powershell</fenced_code_lang>
      </MarkdownBlockBase>
      <MarkdownBlockBase
        xsi:type="MarkdownListBlock"
        item_id="e17dab3e-e93e-46c2-b0fd-fdec0f71bc61"
        item_type="List"
        item_footer=""
        trans_unit_id="e17dab3e-e93e-46c2-b0fd-fdec0f71bc61">
        <inner_list_items>
          <ListItem>
            <MarkdownParagraphBlock
              item_id="71df717d-75e3-457c-ad00-31567b7f1e79"
              item_type="NormalParagraph"
              item_footer="footer_not_set"
              trans_unit_id="71df717d-75e3-457c-ad00-31567b7f1e79">
              <Lines>
                <MarkdownLine>
                  <LineId>03014049-c6bf-4da8-add6-96ac178d81c5</LineId>
                  <paragraph_segments>
                    <MarkdownSegment
                      trans_unit_id="125">
                      <SegmentId>e78ae55a-c4e1-4813-9d6b-1cce38f30552</SegmentId>
                      <InternalNormalItem
                        internal_item_id="1"
                        internal_item_parent_id="125"
                        trans_unit_id="125-1"
                        internal_item_type="Normal">
                        <internal_items />
                      </InternalNormalItem>
                    </MarkdownSegment>
                  </paragraph_segments>
                  <PrefixWSLength>1</PrefixWSLength>
                  <SuffixWSLength>0</SuffixWSLength>
                </MarkdownLine>
              </Lines>
              <paragraph_segments>
                <MarkdownSegment
                  trans_unit_id="125">
                  <SegmentId>e78ae55a-c4e1-4813-9d6b-1cce38f30552</SegmentId>
                  <InternalNormalItem
                    internal_item_id="1"
                    internal_item_parent_id="125"
                    trans_unit_id="125-1"
                    internal_item_type="Normal">
                    <internal_items />
                  </InternalNormalItem>
                </MarkdownSegment>
              </paragraph_segments>
            </MarkdownParagraphBlock>
            <Identifier>3.</Identifier>
            <IndentsLength>
              <int>0</int>
            </IndentsLength>
          </ListItem>
        </inner_list_items>
        <ListType>Number</ListType>
      </MarkdownBlockBase>
      <MarkdownBlockBase
        xsi:type="MarkdownFencedCodeBlock"
        item_id="e3545c50-d53f-475b-8e18-587fd345470a"
        item_type="FencedCodeBlock"
        item_footer=""
        trans_unit_id="e3545c50-d53f-475b-8e18-587fd345470a">
        <codeblock_wraper>  ```</codeblock_wraper>
        <code_block> get-vm | where {$_.State –eq ‘Running’} | stop-vm</code_block>
        <fenced_code_lang>powershell</fenced_code_lang>
      </MarkdownBlockBase>
      <MarkdownBlockBase
        xsi:type="MarkdownHeaderBlock"
        item_id="62e9ecdb-c198-430e-974d-8a4ff9301d38"
        item_type="Header"
        item_footer="footer_not_set"
        trans_unit_id="62e9ecdb-c198-430e-974d-8a4ff9301d38">
        <segment
          trans_unit_id="126">
          <SegmentId>f2853989-d0f5-4ee0-ab53-ae54b291ccf0</SegmentId>
          <InternalNormalItem
            internal_item_id="1"
            internal_item_parent_id="126"
            trans_unit_id="126-1"
            internal_item_type="Normal">
            <internal_items />
          </InternalNormalItem>
        </segment>
        <header_type>Star</header_type>
        <header_level>3</header_level>
      </MarkdownBlockBase>
      <MarkdownBlockBase
        xsi:type="MarkdownParagraphBlock"
        item_id="05278719-a360-42ea-8ce4-74061abdcbc8"
        item_type="NormalParagraph"
        item_footer=""
        trans_unit_id="05278719-a360-42ea-8ce4-74061abdcbc8">
        <Lines>
          <MarkdownLine>
            <LineId>093e2cfc-ee55-4abd-b794-a55dc2bf9c42</LineId>
            <paragraph_segments>
              <MarkdownSegment
                trans_unit_id="127">
                <SegmentId>0ed131af-7a89-4752-b96d-c19197b6ef8b</SegmentId>
                <InternalNormalItem
                  internal_item_id="1"
                  internal_item_parent_id="127"
                  trans_unit_id="127-1"
                  internal_item_type="Normal">
                  <internal_items />
                </InternalNormalItem>
                <CodeSpanItem
                  internal_item_id="2"
                  internal_item_parent_id="127"
                  trans_unit_id="127-2"
                  internal_item_type="CodeSpan">
                  <internal_items />
                  <ItemValue>get-vm</ItemValue>
                </CodeSpanItem>
                <InternalNormalItem
                  internal_item_id="3"
                  internal_item_parent_id="127"
                  trans_unit_id="127-3"
                  internal_item_type="Normal">
                  <internal_items />
                </InternalNormalItem>
                <CodeSpanItem
                  internal_item_id="4"
                  internal_item_parent_id="127"
                  trans_unit_id="127-4"
                  internal_item_type="CodeSpan">
                  <internal_items />
                  <ItemValue>checkpoint-vm</ItemValue>
                </CodeSpanItem>
                <InternalNormalItem
                  internal_item_id="5"
                  internal_item_parent_id="127"
                  trans_unit_id="127-5"
                  internal_item_type="Normal">
                  <internal_items />
                </InternalNormalItem>
              </MarkdownSegment>
              <MarkdownSegment
                trans_unit_id="128">
                <SegmentId>6a7b42e6-29c7-4034-9209-e28c88a68800</SegmentId>
                <InternalNormalItem
                  internal_item_id="1"
                  internal_item_parent_id="128"
                  trans_unit_id="128-1"
                  internal_item_type="Normal">
                  <internal_items />
                </InternalNormalItem>
                <CodeSpanItem
                  internal_item_id="2"
                  internal_item_parent_id="128"
                  trans_unit_id="128-2"
                  internal_item_type="CodeSpan">
                  <internal_items />
                  <ItemValue>-snapshotname</ItemValue>
                </CodeSpanItem>
                <InternalNormalItem
                  internal_item_id="3"
                  internal_item_parent_id="128"
                  trans_unit_id="128-3"
                  internal_item_type="Normal">
                  <internal_items />
                </InternalNormalItem>
              </MarkdownSegment>
              <MarkdownSegment
                trans_unit_id="129">
                <SegmentId>0b4b998d-a1db-4495-8741-2b3498ab5613</SegmentId>
                <InternalNormalItem
                  internal_item_id="1"
                  internal_item_parent_id="129"
                  trans_unit_id="129-1"
                  internal_item_type="Normal">
                  <internal_items />
                </InternalNormalItem>
              </MarkdownSegment>
            </paragraph_segments>
            <PrefixWSLength>0</PrefixWSLength>
            <SuffixWSLength>0</SuffixWSLength>
          </MarkdownLine>
        </Lines>
        <paragraph_segments>
          <MarkdownSegment
            trans_unit_id="127">
            <SegmentId>0ed131af-7a89-4752-b96d-c19197b6ef8b</SegmentId>
            <InternalNormalItem
              internal_item_id="1"
              internal_item_parent_id="127"
              trans_unit_id="127-1"
              internal_item_type="Normal">
              <internal_items />
            </InternalNormalItem>
            <CodeSpanItem
              internal_item_id="2"
              internal_item_parent_id="127"
              trans_unit_id="127-2"
              internal_item_type="CodeSpan">
              <internal_items />
              <ItemValue>get-vm</ItemValue>
            </CodeSpanItem>
            <InternalNormalItem
              internal_item_id="3"
              internal_item_parent_id="127"
              trans_unit_id="127-3"
              internal_item_type="Normal">
              <internal_items />
            </InternalNormalItem>
            <CodeSpanItem
              internal_item_id="4"
              internal_item_parent_id="127"
              trans_unit_id="127-4"
              internal_item_type="CodeSpan">
              <internal_items />
              <ItemValue>checkpoint-vm</ItemValue>
            </CodeSpanItem>
            <InternalNormalItem
              internal_item_id="5"
              internal_item_parent_id="127"
              trans_unit_id="127-5"
              internal_item_type="Normal">
              <internal_items />
            </InternalNormalItem>
          </MarkdownSegment>
          <MarkdownSegment
            trans_unit_id="128">
            <SegmentId>6a7b42e6-29c7-4034-9209-e28c88a68800</SegmentId>
            <InternalNormalItem
              internal_item_id="1"
              internal_item_parent_id="128"
              trans_unit_id="128-1"
              internal_item_type="Normal">
              <internal_items />
            </InternalNormalItem>
            <CodeSpanItem
              internal_item_id="2"
              internal_item_parent_id="128"
              trans_unit_id="128-2"
              internal_item_type="CodeSpan">
              <internal_items />
              <ItemValue>-snapshotname</ItemValue>
            </CodeSpanItem>
            <InternalNormalItem
              internal_item_id="3"
              internal_item_parent_id="128"
              trans_unit_id="128-3"
              internal_item_type="Normal">
              <internal_items />
            </InternalNormalItem>
          </MarkdownSegment>
          <MarkdownSegment
            trans_unit_id="129">
            <SegmentId>0b4b998d-a1db-4495-8741-2b3498ab5613</SegmentId>
            <InternalNormalItem
              internal_item_id="1"
              internal_item_parent_id="129"
              trans_unit_id="129-1"
              internal_item_type="Normal">
              <internal_items />
            </InternalNormalItem>
          </MarkdownSegment>
        </paragraph_segments>
      </MarkdownBlockBase>
      <MarkdownBlockBase
        xsi:type="MarkdownFencedCodeBlock"
        item_id="4d8c4d29-6dfb-4ba1-8a4c-11bd5a55f705"
        item_type="FencedCodeBlock"
        item_footer="footer_not_set"
        trans_unit_id="4d8c4d29-6dfb-4ba1-8a4c-11bd5a55f705">
        <codeblock_wraper> ```</codeblock_wraper>
        <code_block> get-vm -Name VM Name | checkpoint-vm -snapshotname name for snapshot</code_block>
        <fenced_code_lang>powershell</fenced_code_lang>
      </MarkdownBlockBase>
      <MarkdownBlockBase
        xsi:type="MarkdownParagraphBlock"
        item_id="147df2a8-5ebe-4afc-b6fa-dd293e05ab57"
        item_type="NormalParagraph"
        item_footer=""
        trans_unit_id="147df2a8-5ebe-4afc-b6fa-dd293e05ab57">
        <Lines>
          <MarkdownLine>
            <LineId>ea75aca0-cf50-4734-8215-d395334706ab</LineId>
            <paragraph_segments>
              <MarkdownSegment
                trans_unit_id="130">
                <SegmentId>1059aa49-f48c-4f48-b755-57bb53149352</SegmentId>
                <InternalNormalItem
                  internal_item_id="1"
                  internal_item_parent_id="130"
                  trans_unit_id="130-1"
                  internal_item_type="Normal">
                  <internal_items />
                </InternalNormalItem>
              </MarkdownSegment>
            </paragraph_segments>
            <PrefixWSLength>0</PrefixWSLength>
            <SuffixWSLength>0</SuffixWSLength>
          </MarkdownLine>
        </Lines>
        <paragraph_segments>
          <MarkdownSegment
            trans_unit_id="130">
            <SegmentId>1059aa49-f48c-4f48-b755-57bb53149352</SegmentId>
            <InternalNormalItem
              internal_item_id="1"
              internal_item_parent_id="130"
              trans_unit_id="130-1"
              internal_item_type="Normal">
              <internal_items />
            </InternalNormalItem>
          </MarkdownSegment>
        </paragraph_segments>
      </MarkdownBlockBase>
      <MarkdownBlockBase
        xsi:type="MarkdownParagraphBlock"
        item_id="f36dda4d-3bb0-4f0c-b0f7-8f669b688e95"
        item_type="NormalParagraph"
        item_footer=""
        trans_unit_id="f36dda4d-3bb0-4f0c-b0f7-8f669b688e95">
        <Lines>
          <MarkdownLine>
            <LineId>03a73eaf-8eb2-4e39-a72c-e29f854085fd</LineId>
            <paragraph_segments>
              <MarkdownSegment
                trans_unit_id="131">
                <SegmentId>5e49efcc-d735-4a21-a8fc-7eaf12fd58a2</SegmentId>
                <ImageItem
                  internal_item_id="1"
                  internal_item_parent_id="131"
                  trans_unit_id="131-1"
                  internal_item_type="Image">
                  <internal_items />
                  <internal_Image_type>Inline</internal_Image_type>
                  <internal_link_text />
                  <internal_link_url>media\POSH_CP2.png</internal_link_url>
                  <internal_link_title />
                </ImageItem>
              </MarkdownSegment>
            </paragraph_segments>
            <PrefixWSLength>1</PrefixWSLength>
            <SuffixWSLength>0</SuffixWSLength>
          </MarkdownLine>
        </Lines>
        <paragraph_segments>
          <MarkdownSegment
            trans_unit_id="131">
            <SegmentId>5e49efcc-d735-4a21-a8fc-7eaf12fd58a2</SegmentId>
            <ImageItem
              internal_item_id="1"
              internal_item_parent_id="131"
              trans_unit_id="131-1"
              internal_item_type="Image">
              <internal_items />
              <internal_Image_type>Inline</internal_Image_type>
              <internal_link_text />
              <internal_link_url>media\POSH_CP2.png</internal_link_url>
              <internal_link_title />
            </ImageItem>
          </MarkdownSegment>
        </paragraph_segments>
      </MarkdownBlockBase>
      <MarkdownBlockBase
        xsi:type="MarkdownHeaderBlock"
        item_id="64a95f64-9915-4c13-923b-10e9825ec2aa"
        item_type="Header"
        item_footer="footer_not_set"
        trans_unit_id="64a95f64-9915-4c13-923b-10e9825ec2aa">
        <segment
          trans_unit_id="132">
          <SegmentId>fcaca614-da28-4e0c-980b-f1c6ed442424</SegmentId>
          <InternalNormalItem
            internal_item_id="1"
            internal_item_parent_id="132"
            trans_unit_id="132-1"
            internal_item_type="Normal">
            <internal_items />
          </InternalNormalItem>
        </segment>
        <header_type>Star</header_type>
        <header_level>3</header_level>
      </MarkdownBlockBase>
      <MarkdownBlockBase
        xsi:type="MarkdownParagraphBlock"
        item_id="3945f88a-68eb-437a-9df0-9e1f07f7677a"
        item_type="NormalParagraph"
        item_footer=""
        trans_unit_id="3945f88a-68eb-437a-9df0-9e1f07f7677a">
        <Lines>
          <MarkdownLine>
            <LineId>48a18fc6-7952-4a80-9896-b34b1a7fec70</LineId>
            <paragraph_segments>
              <MarkdownSegment
                trans_unit_id="133">
                <SegmentId>17c4ad1f-95d4-4119-ba87-fe8045f79c38</SegmentId>
                <InternalNormalItem
                  internal_item_id="1"
                  internal_item_parent_id="133"
                  trans_unit_id="133-1"
                  internal_item_type="Normal">
                  <internal_items />
                </InternalNormalItem>
              </MarkdownSegment>
              <MarkdownSegment
                trans_unit_id="134">
                <SegmentId>b385b3fd-e524-4375-8c1b-eec7613d1382</SegmentId>
                <InternalNormalItem
                  internal_item_id="1"
                  internal_item_parent_id="134"
                  trans_unit_id="134-1"
                  internal_item_type="Normal">
                  <internal_items />
                </InternalNormalItem>
              </MarkdownSegment>
            </paragraph_segments>
            <PrefixWSLength>0</PrefixWSLength>
            <SuffixWSLength>0</SuffixWSLength>
          </MarkdownLine>
        </Lines>
        <paragraph_segments>
          <MarkdownSegment
            trans_unit_id="133">
            <SegmentId>17c4ad1f-95d4-4119-ba87-fe8045f79c38</SegmentId>
            <InternalNormalItem
              internal_item_id="1"
              internal_item_parent_id="133"
              trans_unit_id="133-1"
              internal_item_type="Normal">
              <internal_items />
            </InternalNormalItem>
          </MarkdownSegment>
          <MarkdownSegment
            trans_unit_id="134">
            <SegmentId>b385b3fd-e524-4375-8c1b-eec7613d1382</SegmentId>
            <InternalNormalItem
              internal_item_id="1"
              internal_item_parent_id="134"
              trans_unit_id="134-1"
              internal_item_type="Normal">
              <internal_items />
            </InternalNormalItem>
          </MarkdownSegment>
        </paragraph_segments>
      </MarkdownBlockBase>
      <MarkdownBlockBase
        xsi:type="MarkdownListBlock"
        item_id="0162e468-8716-4bb7-a1d1-71d53fbd0615"
        item_type="List"
        item_footer=""
        trans_unit_id="0162e468-8716-4bb7-a1d1-71d53fbd0615">
        <inner_list_items>
          <ListItem>
            <MarkdownParagraphBlock
              item_id="b41f5d72-3144-4dbb-ba00-8ba68276084b"
              item_type="NormalParagraph"
              item_footer="footer_not_set"
              trans_unit_id="b41f5d72-3144-4dbb-ba00-8ba68276084b">
              <Lines>
                <MarkdownLine>
                  <LineId>605bd92a-21f1-4ea0-871f-8b225ad38612</LineId>
                  <paragraph_segments>
                    <MarkdownSegment
                      trans_unit_id="135">
                      <SegmentId>0ff6f760-a4ac-4daf-bf69-c4f8e7528260</SegmentId>
                      <InternalNormalItem
                        internal_item_id="1"
                        internal_item_parent_id="135"
                        trans_unit_id="135-1"
                        internal_item_type="Normal">
                        <internal_items />
                      </InternalNormalItem>
                      <MarkdownInternalBoldItem
                        internal_item_id="2"
                        internal_item_parent_id="135"
                        trans_unit_id="135-2"
                        internal_item_type="Bold">
                        <internal_items />
                        <internal_itatic_bold_item_type>Star</internal_itatic_bold_item_type>
                      </MarkdownInternalBoldItem>
                      <InternalNormalItem
                        internal_item_id="3"
                        internal_item_parent_id="135"
                        trans_unit_id="135-3"
                        internal_item_type="Normal">
                        <internal_items />
                      </InternalNormalItem>
                    </MarkdownSegment>
                  </paragraph_segments>
                  <PrefixWSLength>1</PrefixWSLength>
                  <SuffixWSLength>0</SuffixWSLength>
                </MarkdownLine>
              </Lines>
              <paragraph_segments>
                <MarkdownSegment
                  trans_unit_id="135">
                  <SegmentId>0ff6f760-a4ac-4daf-bf69-c4f8e7528260</SegmentId>
                  <InternalNormalItem
                    internal_item_id="1"
                    internal_item_parent_id="135"
                    trans_unit_id="135-1"
                    internal_item_type="Normal">
                    <internal_items />
                  </InternalNormalItem>
                  <MarkdownInternalBoldItem
                    internal_item_id="2"
                    internal_item_parent_id="135"
                    trans_unit_id="135-2"
                    internal_item_type="Bold">
                    <internal_items />
                    <internal_itatic_bold_item_type>Star</internal_itatic_bold_item_type>
                  </MarkdownInternalBoldItem>
                  <InternalNormalItem
                    internal_item_id="3"
                    internal_item_parent_id="135"
                    trans_unit_id="135-3"
                    internal_item_type="Normal">
                    <internal_items />
                  </InternalNormalItem>
                </MarkdownSegment>
              </paragraph_segments>
            </MarkdownParagraphBlock>
            <Identifier>1.</Identifier>
            <IndentsLength>
              <int>0</int>
            </IndentsLength>
          </ListItem>
          <ListItem>
            <MarkdownParagraphBlock
              item_id="324f5c14-5e12-4f98-87ce-9e36c84e344f"
              item_type="NormalParagraph"
              item_footer="footer_not_set"
              trans_unit_id="324f5c14-5e12-4f98-87ce-9e36c84e344f">
              <Lines>
                <MarkdownLine>
                  <LineId>0520f376-aa9b-4223-9bef-251fe23db3e4</LineId>
                  <paragraph_segments>
                    <MarkdownSegment
                      trans_unit_id="136">
                      <SegmentId>674b25df-6e78-46da-aed5-89283c1f74e7</SegmentId>
                      <InternalNormalItem
                        internal_item_id="1"
                        internal_item_parent_id="136"
                        trans_unit_id="136-1"
                        internal_item_type="Normal">
                        <internal_items />
                      </InternalNormalItem>
                    </MarkdownSegment>
                    <MarkdownSegment
                      trans_unit_id="137">
                      <SegmentId>86d6c8d5-a96f-41ae-b3d1-78e4ab04ff8d</SegmentId>
                      <InternalNormalItem
                        internal_item_id="1"
                        internal_item_parent_id="137"
                        trans_unit_id="137-1"
                        internal_item_type="Normal">
                        <internal_items />
                      </InternalNormalItem>
                      <LinkItem
                        internal_item_id="2"
                        internal_item_parent_id="137"
                        trans_unit_id="137-2"
                        internal_item_type="Link">
                        <internal_items />
                        <internal_link_type>Inline</internal_link_type>
                        <internal_link_text>New-VM</internal_link_text>
                        <internal_link_url>https://technet.microsoft.com/en-us/library/hh848537.aspx</internal_link_url>
                        <internal_link_title />
                      </LinkItem>
                      <InternalNormalItem
                        internal_item_id="3"
                        internal_item_parent_id="137"
                        trans_unit_id="137-3"
                        internal_item_type="Normal">
                        <internal_items />
                      </InternalNormalItem>
                    </MarkdownSegment>
                  </paragraph_segments>
                  <PrefixWSLength>1</PrefixWSLength>
                  <SuffixWSLength>0</SuffixWSLength>
                </MarkdownLine>
              </Lines>
              <paragraph_segments>
                <MarkdownSegment
                  trans_unit_id="136">
                  <SegmentId>674b25df-6e78-46da-aed5-89283c1f74e7</SegmentId>
                  <InternalNormalItem
                    internal_item_id="1"
                    internal_item_parent_id="136"
                    trans_unit_id="136-1"
                    internal_item_type="Normal">
                    <internal_items />
                  </InternalNormalItem>
                </MarkdownSegment>
                <MarkdownSegment
                  trans_unit_id="137">
                  <SegmentId>86d6c8d5-a96f-41ae-b3d1-78e4ab04ff8d</SegmentId>
                  <InternalNormalItem
                    internal_item_id="1"
                    internal_item_parent_id="137"
                    trans_unit_id="137-1"
                    internal_item_type="Normal">
                    <internal_items />
                  </InternalNormalItem>
                  <LinkItem
                    internal_item_id="2"
                    internal_item_parent_id="137"
                    trans_unit_id="137-2"
                    internal_item_type="Link">
                    <internal_items />
                    <internal_link_type>Inline</internal_link_type>
                    <internal_link_text>New-VM</internal_link_text>
                    <internal_link_url>https://technet.microsoft.com/en-us/library/hh848537.aspx</internal_link_url>
                    <internal_link_title />
                  </LinkItem>
                  <InternalNormalItem
                    internal_item_id="3"
                    internal_item_parent_id="137"
                    trans_unit_id="137-3"
                    internal_item_type="Normal">
                    <internal_items />
                  </InternalNormalItem>
                </MarkdownSegment>
              </paragraph_segments>
            </MarkdownParagraphBlock>
            <Identifier>2.</Identifier>
            <IndentsLength>
              <int>0</int>
            </IndentsLength>
          </ListItem>
        </inner_list_items>
        <ListType>Number</ListType>
      </MarkdownBlockBase>
      <MarkdownBlockBase
        xsi:type="MarkdownFencedCodeBlock"
        item_id="87c57f7c-fdae-4100-9263-7ec4ad012db8"
        item_type="FencedCodeBlock"
        item_footer=""
        trans_unit_id="87c57f7c-fdae-4100-9263-7ec4ad012db8">
        <codeblock_wraper>  ```</codeblock_wraper>
        <code_block> $VMName = "VMNAME"

 $VM = @{
     Name = $VMName 
     MemoryStartupBytes = 2147483648
     Generation = 2
     NewVHDPath = "C:\Virtual Machines\$VMName\$VMName.vhdx"
     NewVHDSizeBytes = 53687091200
     BootDevice = "VHD"
     Path = "C:\Virtual Machines\$VMName "
     SwitchName = (get-vmswitch).Name[0]
 }

 New-VM @VM</code_block>
        <fenced_code_lang>powershell</fenced_code_lang>
      </MarkdownBlockBase>
      <MarkdownBlockBase
        xsi:type="MarkdownHeaderBlock"
        item_id="3c6705c2-925a-4c63-bea0-3a1658041723"
        item_type="Header"
        item_footer="footer_not_set"
        trans_unit_id="3c6705c2-925a-4c63-bea0-3a1658041723">
        <segment
          trans_unit_id="138">
          <SegmentId>50e0244d-2c40-4499-8a73-5f290eb2e735</SegmentId>
          <InternalNormalItem
            internal_item_id="1"
            internal_item_parent_id="138"
            trans_unit_id="138-1"
            internal_item_type="Normal">
            <internal_items />
          </InternalNormalItem>
        </segment>
        <header_type>Star</header_type>
        <header_level>2</header_level>
      </MarkdownBlockBase>
      <MarkdownBlockBase
        xsi:type="MarkdownParagraphBlock"
        item_id="7abb5aa4-51aa-4fae-8a7a-01206aa70ec2"
        item_type="NormalParagraph"
        item_footer="&#xA;&#xA;"
        trans_unit_id="7abb5aa4-51aa-4fae-8a7a-01206aa70ec2">
        <Lines>
          <MarkdownLine>
            <LineId>805902eb-62a2-4da6-96be-ef99246af7d0</LineId>
            <paragraph_segments>
              <MarkdownSegment
                trans_unit_id="139">
                <SegmentId>843da879-bec7-4780-a26c-0d3640694faf</SegmentId>
                <InternalNormalItem
                  internal_item_id="1"
                  internal_item_parent_id="139"
                  trans_unit_id="139-1"
                  internal_item_type="Normal">
                  <internal_items />
                </InternalNormalItem>
              </MarkdownSegment>
              <MarkdownSegment
                trans_unit_id="140">
                <SegmentId>919e1792-b314-45b5-bb61-70f4f65190f3</SegmentId>
                <InternalNormalItem
                  internal_item_id="1"
                  internal_item_parent_id="140"
                  trans_unit_id="140-1"
                  internal_item_type="Normal">
                  <internal_items />
                </InternalNormalItem>
                <LinkItem
                  internal_item_id="2"
                  internal_item_parent_id="140"
                  trans_unit_id="140-2"
                  internal_item_type="Link">
                  <internal_items />
                  <internal_link_type>Inline</internal_link_type>
                  <internal_link_text>Hyper-V Cmdlets in Windows PowerShell reference</internal_link_text>
                  <internal_link_url>https://technet.microsoft.com/%5Clibrary/Hh848559.aspx</internal_link_url>
                  <internal_link_title />
                </LinkItem>
                <InternalNormalItem
                  internal_item_id="3"
                  internal_item_parent_id="140"
                  trans_unit_id="140-3"
                  internal_item_type="Normal">
                  <internal_items />
                </InternalNormalItem>
              </MarkdownSegment>
            </paragraph_segments>
            <PrefixWSLength>0</PrefixWSLength>
            <SuffixWSLength>0</SuffixWSLength>
          </MarkdownLine>
        </Lines>
        <paragraph_segments>
          <MarkdownSegment
            trans_unit_id="139">
            <SegmentId>843da879-bec7-4780-a26c-0d3640694faf</SegmentId>
            <InternalNormalItem
              internal_item_id="1"
              internal_item_parent_id="139"
              trans_unit_id="139-1"
              internal_item_type="Normal">
              <internal_items />
            </InternalNormalItem>
          </MarkdownSegment>
          <MarkdownSegment
            trans_unit_id="140">
            <SegmentId>919e1792-b314-45b5-bb61-70f4f65190f3</SegmentId>
            <InternalNormalItem
              internal_item_id="1"
              internal_item_parent_id="140"
              trans_unit_id="140-1"
              internal_item_type="Normal">
              <internal_items />
            </InternalNormalItem>
            <LinkItem
              internal_item_id="2"
              internal_item_parent_id="140"
              trans_unit_id="140-2"
              internal_item_type="Link">
              <internal_items />
              <internal_link_type>Inline</internal_link_type>
              <internal_link_text>Hyper-V Cmdlets in Windows PowerShell reference</internal_link_text>
              <internal_link_url>https://technet.microsoft.com/%5Clibrary/Hh848559.aspx</internal_link_url>
              <internal_link_title />
            </LinkItem>
            <InternalNormalItem
              internal_item_id="3"
              internal_item_parent_id="140"
              trans_unit_id="140-3"
              internal_item_type="Normal">
              <internal_items />
            </InternalNormalItem>
          </MarkdownSegment>
        </paragraph_segments>
      </MarkdownBlockBase>
    </ArrayOfMarkdownBlockBase>
  </block_element>
  <references>
    <ArrayOfMarkdownLinkedReference xmlns:xsi="http://www.w3.org/2001/XMLSchema-instance" xmlns:xsd="http://www.w3.org/2001/XMLSchema" />
  </references>
</markdown_skeleton_root>