<markdown_skeleton_root>
  <block_element>
    <ArrayOfMarkdownBlockBase xmlns:xsi="http://www.w3.org/2001/XMLSchema-instance" xmlns:xsd="http://www.w3.org/2001/XMLSchema">
      <MarkdownBlockBase
        xsi:type="MarkdownParagraphBlock"
        item_id="99ed7b51-8c91-4776-8fb3-a047a7404de1"
        item_type="NormalParagraph"
        item_footer="">
        <paragraph_segments>
          <MarkdownSegment>
            <SegmentId>6e51f9bc-b64f-4169-831f-d7cd9fad8bb0</SegmentId>
            <InternalNormalItem
              internal_item_id="37bf77de-5d29-4b4f-b9f0-3d150ee5ebe3"
              internal_item_type="Normal">
              <internal_items />
            </InternalNormalItem>
          </MarkdownSegment>
        </paragraph_segments>
      </MarkdownBlockBase>
      <MarkdownBlockBase
        xsi:type="MarkdownHeaderBlock"
        item_id="a914adbc-ac6c-4743-803c-7d8d4efc5e98"
        item_type="Header"
        item_footer="footer_not_set">
        <header_type>Star</header_type>
        <header_level>1</header_level>
      </MarkdownBlockBase>
      <MarkdownBlockBase
        xsi:type="MarkdownParagraphBlock"
        item_id="2cae6335-752f-45dc-a307-9b6b5759e5c9"
        item_type="NormalParagraph"
        item_footer="">
        <paragraph_segments>
          <MarkdownSegment>
            <SegmentId>252b06af-d87d-4c1c-b469-cec640f5bec4</SegmentId>
            <InternalNormalItem
              internal_item_id="31ecbb5e-d879-4ac8-a005-5bdcfa9d0222"
              internal_item_type="Normal">
              <internal_items />
            </InternalNormalItem>
          </MarkdownSegment>
        </paragraph_segments>
      </MarkdownBlockBase>
      <MarkdownBlockBase
        xsi:type="MarkdownHeaderBlock"
        item_id="ce40141f-7b6b-4268-8795-c1e70ff0aa44"
        item_type="Header"
        item_footer="footer_not_set">
        <header_type>Star</header_type>
        <header_level>2</header_level>
      </MarkdownBlockBase>
      <MarkdownBlockBase
        xsi:type="MarkdownParagraphBlock"
        item_id="af0b4021-3292-41db-8f2b-0ef57a5ade69"
        item_type="NormalParagraph"
        item_footer="">
        <paragraph_segments>
          <MarkdownSegment>
            <SegmentId>a9362a68-13e9-4cc2-a817-8e391e83a50a</SegmentId>
            <InternalNormalItem
              internal_item_id="25e9c709-82bf-4089-8551-cd32ce2fc220"
              internal_item_type="Normal">
              <internal_items />
            </InternalNormalItem>
          </MarkdownSegment>
          <MarkdownSegment>
            <SegmentId>5a19f416-d77d-4fa3-a4c7-4c3c2e3ddd4d</SegmentId>
            <InternalNormalItem
              internal_item_id="97c42b91-adaa-4119-bc29-9b80c542c1f3"
              internal_item_type="Normal">
              <internal_items />
            </InternalNormalItem>
          </MarkdownSegment>
          <MarkdownSegment>
            <SegmentId>abc376c9-a41a-45bc-afd7-6d60a5f65913</SegmentId>
            <InternalNormalItem
              internal_item_id="9a2f62af-49a8-4bc3-a0e0-3b5b5af77882"
              internal_item_type="Normal">
              <internal_items />
            </InternalNormalItem>
          </MarkdownSegment>
          <MarkdownSegment>
            <SegmentId>e7b0d176-228a-49ee-8045-7b22b5060a86</SegmentId>
            <InternalNormalItem
              internal_item_id="0c140ed4-a80f-44d1-860b-ca09189cad67"
              internal_item_type="Normal">
              <internal_items />
            </InternalNormalItem>
          </MarkdownSegment>
        </paragraph_segments>
      </MarkdownBlockBase>
      <MarkdownBlockBase
        xsi:type="MarkdownParagraphBlock"
        item_id="fd75be33-9c34-45f1-b5cf-d1d5eff47676"
        item_type="NormalParagraph"
        item_footer="">
        <paragraph_segments>
          <MarkdownSegment>
            <SegmentId>a8fcdcce-4f5c-41fa-a668-68b23e557f10</SegmentId>
            <InternalNormalItem
              internal_item_id="d1c7422c-18ed-4020-97e5-c024756aa7ad"
              internal_item_type="Normal">
              <internal_items />
            </InternalNormalItem>
          </MarkdownSegment>
        </paragraph_segments>
      </MarkdownBlockBase>
      <MarkdownBlockBase
        xsi:type="MarkdownFencedCodeBlock"
        item_id="e97e6a4f-957f-48ce-a320-19a8bd264f40"
        item_type="FencedCodeBlock"
        item_footer="">
        <codeblock_wraper>```</codeblock_wraper>
        <code_block>Enter-PSSession -VMName VMName
Invoke-Command -VMName VMName -ScriptBlock { commands }</code_block>
        <fenced_code_lang> PowerShell</fenced_code_lang>
      </MarkdownBlockBase>
      <MarkdownBlockBase
        xsi:type="MarkdownParagraphBlock"
        item_id="d02a3848-618b-436b-935e-ea39ea07fca7"
        item_type="NormalParagraph"
        item_footer="footer_not_set">
        <paragraph_segments>
          <MarkdownSegment>
            <SegmentId>0a9b322e-08c8-4a28-8d09-22fb0a6e1150</SegmentId>
            <InternalNormalItem
              internal_item_id="ebf045cc-fa03-4efa-8923-21e96eb99fa7"
              internal_item_type="Normal">
              <internal_items />
            </InternalNormalItem>
          </MarkdownSegment>
        </paragraph_segments>
      </MarkdownBlockBase>
      <MarkdownBlockBase
        xsi:type="MarkdownListBlock"
        item_id="0318affd-22e1-4831-bb6e-78cd796ecc79"
        item_type="List"
        item_footer="">
        <inner_list_items>
          <ListItem>
            <MarkdownParagraphBlock
              item_id="1811c375-b3b1-441b-9a4e-afef73770e9c"
              item_type="NormalParagraph"
              item_footer="footer_not_set">
              <paragraph_segments>
                <MarkdownSegment>
                  <SegmentId>3a251519-2935-4eca-a323-44834ceb6573</SegmentId>
                  <InternalNormalItem
                    internal_item_id="ad451d7f-1e81-46f5-baa6-ecc3b41d5848"
                    internal_item_type="Normal">
                    <internal_items />
                  </InternalNormalItem>
                </MarkdownSegment>
              </paragraph_segments>
            </MarkdownParagraphBlock>
            <Identifier>- </Identifier>
          </ListItem>
          <ListItem>
            <MarkdownParagraphBlock
              item_id="da3cc7e1-9645-40d9-90b2-a0633742b0e0"
              item_type="NormalParagraph"
              item_footer="footer_not_set">
              <paragraph_segments>
                <MarkdownSegment>
                  <SegmentId>9f46c59c-31fe-4df3-b804-fae95248a2ef</SegmentId>
                  <InternalNormalItem
                    internal_item_id="a920e919-3118-4681-8984-09565dc2e744"
                    internal_item_type="Normal">
                    <internal_items />
                  </InternalNormalItem>
                </MarkdownSegment>
              </paragraph_segments>
            </MarkdownParagraphBlock>
            <Identifier>- </Identifier>
          </ListItem>
        </inner_list_items>
        <ListType>Charactor</ListType>
      </MarkdownBlockBase>
      <MarkdownBlockBase
        xsi:type="MarkdownParagraphBlock"
        item_id="85f76ce0-0608-4f76-8616-4642f75fa78f"
        item_type="NormalParagraph"
        item_footer="">
        <paragraph_segments>
          <MarkdownSegment>
            <SegmentId>e21f5858-3d0e-4f32-bf43-ae9ac39d415c</SegmentId>
            <InternalNormalItem
              internal_item_id="58371809-516e-49dc-8e2e-1f4bdb80f4df"
              internal_item_type="Normal">
              <internal_items />
            </InternalNormalItem>
          </MarkdownSegment>
          <MarkdownSegment>
            <SegmentId>f1932bf0-beec-473e-85f1-1967a9cb3ffd</SegmentId>
            <InternalNormalItem
              internal_item_id="4f3fd06d-8c23-493b-a387-4dc18923c619"
              internal_item_type="Normal">
              <internal_items />
            </InternalNormalItem>
          </MarkdownSegment>
          <MarkdownSegment>
            <SegmentId>a82e8451-e783-441e-bfd9-b576755af920</SegmentId>
            <InternalNormalItem
              internal_item_id="8190f76f-c500-495f-9ef5-5351d8d52d11"
              internal_item_type="Normal">
              <internal_items />
            </InternalNormalItem>
          </MarkdownSegment>
        </paragraph_segments>
      </MarkdownBlockBase>
      <MarkdownBlockBase
        xsi:type="MarkdownParagraphBlock"
        item_id="59700ddf-b635-4f5b-887a-cc53413fbe2d"
        item_type="NormalParagraph"
        item_footer="">
        <paragraph_segments>
          <MarkdownSegment>
            <SegmentId>80c17fc1-f206-4f50-8230-b3774528b3f1</SegmentId>
            <InternalNormalItem
              internal_item_id="b4d4f794-098f-4e0f-b785-1383fbb5d455"
              internal_item_type="Normal">
              <internal_items />
            </InternalNormalItem>
          </MarkdownSegment>
          <MarkdownSegment>
            <SegmentId>4c23be55-b533-4ce8-bfe3-2debfc104292</SegmentId>
            <InternalNormalItem
              internal_item_id="ee37aacf-ab18-49fe-bebc-b104137ab7a7"
              internal_item_type="Normal">
              <internal_items />
            </InternalNormalItem>
          </MarkdownSegment>
          <MarkdownSegment>
            <SegmentId>6a081349-8b6f-4e28-8f14-b097ad59a975</SegmentId>
            <InternalNormalItem
              internal_item_id="643e041c-c3fa-4ceb-8696-b8da6aa930de"
              internal_item_type="Normal">
              <internal_items />
            </InternalNormalItem>
          </MarkdownSegment>
        </paragraph_segments>
      </MarkdownBlockBase>
      <MarkdownBlockBase
        xsi:type="MarkdownHeaderBlock"
        item_id="a3c21c4e-8821-4997-a966-0469656985b5"
        item_type="Header"
        item_footer="footer_not_set">
        <header_type>Star</header_type>
        <header_level>4</header_level>
      </MarkdownBlockBase>
      <MarkdownBlockBase
        xsi:type="MarkdownListBlock"
        item_id="2fa191be-c8ff-4a15-b8c0-7555bd18917a"
        item_type="List"
        item_footer="&#xA;">
        <inner_list_items>
          <ListItem>
            <MarkdownParagraphBlock
              item_id="b508d656-f226-40f1-99c5-9a712b726dd5"
              item_type="NormalParagraph"
              item_footer="footer_not_set">
              <paragraph_segments>
                <MarkdownSegment>
                  <SegmentId>2a66915a-f126-4f19-bf14-1986cff1cfcd</SegmentId>
                  <InternalNormalItem
                    internal_item_id="70af59e1-7407-4c94-935e-1638b8c4c9d9"
                    internal_item_type="Normal">
                    <internal_items />
                  </InternalNormalItem>
                </MarkdownSegment>
              </paragraph_segments>
            </MarkdownParagraphBlock>
            <Identifier>- </Identifier>
          </ListItem>
          <ListItem>
            <MarkdownParagraphBlock
              item_id="57bcf2bb-65e5-4d79-a61b-4ba324a64d8e"
              item_type="NormalParagraph"
              item_footer="footer_not_set">
              <paragraph_segments>
                <MarkdownSegment>
                  <SegmentId>273c1a02-3d27-4a4a-a965-ea41c30f3f8f</SegmentId>
                  <InternalNormalItem
                    internal_item_id="c9ce2f59-2115-4e03-85e9-a0609ecf8ca3"
                    internal_item_type="Normal">
                    <internal_items />
                  </InternalNormalItem>
                </MarkdownSegment>
              </paragraph_segments>
            </MarkdownParagraphBlock>
            <Identifier>- </Identifier>
          </ListItem>
          <ListItem>
            <MarkdownParagraphBlock
              item_id="d58f044e-c505-4cb6-a897-acec15e5bd90"
              item_type="NormalParagraph"
              item_footer="footer_not_set">
              <paragraph_segments>
                <MarkdownSegment>
                  <SegmentId>55d009ff-a880-4f9e-85d0-a0fe25e4fc7c</SegmentId>
                  <InternalNormalItem
                    internal_item_id="fdd35b79-b083-427c-8973-6ce5beac780c"
                    internal_item_type="Normal">
                    <internal_items />
                  </InternalNormalItem>
                </MarkdownSegment>
              </paragraph_segments>
            </MarkdownParagraphBlock>
            <Identifier>- </Identifier>
          </ListItem>
          <ListItem>
            <MarkdownParagraphBlock
              item_id="ea5c9d5a-8adf-46f8-9f0b-e093e3659e7b"
              item_type="NormalParagraph"
              item_footer="footer_not_set">
              <paragraph_segments>
                <MarkdownSegment>
                  <SegmentId>4c402fb9-a024-4ee1-8dd0-cc8558f9222d</SegmentId>
                  <InternalNormalItem
                    internal_item_id="a3da5b24-446c-420f-b34d-5b382e2e5dec"
                    internal_item_type="Normal">
                    <internal_items />
                  </InternalNormalItem>
                </MarkdownSegment>
              </paragraph_segments>
            </MarkdownParagraphBlock>
            <Identifier>- </Identifier>
          </ListItem>
        </inner_list_items>
        <ListType>Charactor</ListType>
      </MarkdownBlockBase>
      <MarkdownBlockBase
        xsi:type="MarkdownHeaderBlock"
        item_id="0ef93d7e-b5db-4000-ad59-617dd491869b"
        item_type="Header"
        item_footer="footer_not_set">
        <header_type>Star</header_type>
        <header_level>2</header_level>
      </MarkdownBlockBase>
      <MarkdownBlockBase
        xsi:type="MarkdownParagraphBlock"
        item_id="a1929a1a-f59f-4e04-ae0f-c2e221e0ed42"
        item_type="NormalParagraph"
        item_footer="">
        <paragraph_segments>
          <MarkdownSegment>
            <SegmentId>21234c65-a00c-426a-a8a6-af6022a62b43</SegmentId>
            <InternalNormalItem
              internal_item_id="e821f88c-7866-48c2-945b-481a68a40637"
              internal_item_type="Normal">
              <internal_items />
            </InternalNormalItem>
          </MarkdownSegment>
          <MarkdownSegment>
            <SegmentId>82477760-c34d-4b74-8b14-d4c05496cfd8</SegmentId>
            <InternalNormalItem
              internal_item_id="d0bb5623-c78e-4dd3-a131-25089c303fcd"
              internal_item_type="Normal">
              <internal_items />
            </InternalNormalItem>
          </MarkdownSegment>
        </paragraph_segments>
      </MarkdownBlockBase>
      <MarkdownBlockBase
        xsi:type="MarkdownParagraphBlock"
        item_id="e2f07e5f-96dd-4aee-b705-b28475538307"
        item_type="NormalParagraph"
        item_footer="">
        <paragraph_segments>
          <MarkdownSegment>
            <SegmentId>f1cbf42e-34c3-4995-b8f5-5307e2f69a07</SegmentId>
            <InternalNormalItem
              internal_item_id="94dbc632-49a6-42a4-9af7-c3325a8d2c63"
              internal_item_type="Normal">
              <internal_items />
            </InternalNormalItem>
          </MarkdownSegment>
          <MarkdownSegment>
            <SegmentId>07e88086-b7c5-40c3-9218-d388805a94ec</SegmentId>
            <InternalNormalItem
              internal_item_id="22bcaf9e-b08e-459b-be5c-8e8f1b26f222"
              internal_item_type="Normal">
              <internal_items />
            </InternalNormalItem>
          </MarkdownSegment>
        </paragraph_segments>
      </MarkdownBlockBase>
      <MarkdownBlockBase
        xsi:type="MarkdownHeaderBlock"
        item_id="e78e2f59-a73a-4329-babf-c69df21455e1"
        item_type="Header"
        item_footer="footer_not_set">
        <header_type>Star</header_type>
        <header_level>2</header_level>
      </MarkdownBlockBase>
      <MarkdownBlockBase
        xsi:type="MarkdownParagraphBlock"
        item_id="ccb2c019-acd2-439e-b328-574f0d94cadb"
        item_type="NormalParagraph"
        item_footer="&#xA;">
        <paragraph_segments>
          <MarkdownSegment>
            <SegmentId>bd9af982-22e7-4feb-8372-885d1f9094e5</SegmentId>
            <InternalNormalItem
              internal_item_id="b38a8cf4-4ff5-41f7-ad3a-049206856b1e"
              internal_item_type="Normal">
              <internal_items />
            </InternalNormalItem>
          </MarkdownSegment>
          <MarkdownSegment>
            <SegmentId>06c4ddc1-dcbc-4699-bde0-4e9df2941963</SegmentId>
            <InternalNormalItem
              internal_item_id="1031be7f-4063-4014-9168-39c71d1ec1fb"
              internal_item_type="Normal">
              <internal_items />
            </InternalNormalItem>
          </MarkdownSegment>
          <MarkdownSegment>
            <SegmentId>ea2c0e91-3af1-4424-849b-3f84cfe4420f</SegmentId>
            <InternalNormalItem
              internal_item_id="9e805707-34e6-4305-b05e-5c3b4a771ca8"
              internal_item_type="Normal">
              <internal_items />
            </InternalNormalItem>
          </MarkdownSegment>
          <MarkdownSegment>
            <SegmentId>f3684411-3e26-4e56-a1f5-e1048d589743</SegmentId>
            <InternalNormalItem
              internal_item_id="dd7ec792-413c-4ee9-aca7-cc0b1a229240"
              internal_item_type="Normal">
              <internal_items />
            </InternalNormalItem>
          </MarkdownSegment>
          <MarkdownSegment>
            <SegmentId>7b95a9cc-9334-42d9-841a-6c25d9325c09</SegmentId>
            <InternalNormalItem
              internal_item_id="ca48adf6-10b7-4631-85f4-efe268428536"
              internal_item_type="Normal">
              <internal_items />
            </InternalNormalItem>
          </MarkdownSegment>
        </paragraph_segments>
      </MarkdownBlockBase>
      <MarkdownBlockBase
        xsi:type="MarkdownBlockQuote"
        item_id="9f54130a-64dd-44b7-92ab-331ece0430d1"
        item_type="BlockQuote"
        item_footer="&#xA;">
        <MarkdownParagraphBlock
          item_id="7554bc77-a807-437d-a234-c62866ec8415"
          item_type="NormalParagraph"
          item_footer="footer_not_set">
          <paragraph_segments>
            <MarkdownSegment>
              <SegmentId>469964cd-54e0-4555-b934-a4ca569658de</SegmentId>
              <MarkdownInternalBoldItem
                internal_item_id="3b8c6675-7795-4436-ab4b-00e38be57ce8"
                internal_item_type="Bold">
                <internal_items />
                <internal_itatic_bold_item_type>Star</internal_itatic_bold_item_type>
              </MarkdownInternalBoldItem>
              <InternalNormalItem
                internal_item_id="50d7287c-0afc-4ce9-adf3-6765cc8702e6"
                internal_item_type="Normal">
                <internal_items />
              </InternalNormalItem>
            </MarkdownSegment>
          </paragraph_segments>
        </MarkdownParagraphBlock>
      </MarkdownBlockBase>
      <MarkdownBlockBase
        xsi:type="MarkdownHeaderBlock"
        item_id="ffb8f77a-fb73-481e-8200-b8a46d5a72db"
        item_type="Header"
        item_footer="footer_not_set">
        <header_type>Star</header_type>
        <header_level>2</header_level>
      </MarkdownBlockBase>
      <MarkdownBlockBase
        xsi:type="MarkdownListBlock"
        item_id="64681185-7a42-4ff6-b475-b556bdcf24e3"
        item_type="List"
        item_footer="&#xA;">
        <inner_list_items>
          <ListItem>
            <MarkdownParagraphBlock
              item_id="e303df51-a9ad-42f6-b625-83a42631c9a1"
              item_type="NormalParagraph"
              item_footer="">
              <paragraph_segments>
                <MarkdownSegment>
                  <SegmentId>c9121bf2-fdad-4002-8f0e-282b30a57827</SegmentId>
                  <MarkdownInternalBoldItem
                    internal_item_id="fe0cc157-58f1-49ef-9891-6e08960bacb5"
                    internal_item_type="Bold">
                    <internal_items />
                    <internal_itatic_bold_item_type>Star</internal_itatic_bold_item_type>
                  </MarkdownInternalBoldItem>
                  <InternalNormalItem
                    internal_item_id="956ea0cc-352d-4069-8535-3a6679326c3a"
                    internal_item_type="Normal">
                    <internal_items />
                  </InternalNormalItem>
                </MarkdownSegment>
                <MarkdownSegment>
                  <SegmentId>3eff9adc-4f55-4bc8-ba41-e729e6a76a42</SegmentId>
                  <InternalNormalItem
                    internal_item_id="e0bb9c10-d852-49c4-b478-300539f0d6bc"
                    internal_item_type="Normal">
                    <internal_items />
                  </InternalNormalItem>
                </MarkdownSegment>
              </paragraph_segments>
            </MarkdownParagraphBlock>
            <Identifier>- </Identifier>
          </ListItem>
          <ListItem>
            <MarkdownParagraphBlock
              item_id="390ed364-5b27-42ca-99d0-ae210f6696bd"
              item_type="NormalParagraph"
              item_footer="">
              <paragraph_segments>
                <MarkdownSegment>
                  <SegmentId>1a92a602-2cd5-459f-9e5e-d1a57f201d89</SegmentId>
                  <MarkdownInternalBoldItem
                    internal_item_id="7aafa06f-4171-49cf-bb7b-767ca538bfa3"
                    internal_item_type="Bold">
                    <internal_items />
                    <internal_itatic_bold_item_type>Star</internal_itatic_bold_item_type>
                  </MarkdownInternalBoldItem>
                  <InternalNormalItem
                    internal_item_id="5a123abd-0b3d-4b25-8d84-9cdd63e70bdd"
                    internal_item_type="Normal">
                    <internal_items />
                  </InternalNormalItem>
                </MarkdownSegment>
                <MarkdownSegment>
                  <SegmentId>e25a1806-1ac4-442f-b9a5-fa95d15dc2a2</SegmentId>
                  <InternalNormalItem
                    internal_item_id="edc9e1cb-b60b-44f5-805c-17a8537cfd59"
                    internal_item_type="Normal">
                    <internal_items />
                  </InternalNormalItem>
                </MarkdownSegment>
              </paragraph_segments>
            </MarkdownParagraphBlock>
            <Identifier>- </Identifier>
          </ListItem>
          <ListItem>
            <MarkdownParagraphBlock
              item_id="f5cc1121-3a5f-4bc3-bf59-e254a169b0af"
              item_type="NormalParagraph"
              item_footer="footer_not_set">
              <paragraph_segments>
                <MarkdownSegment>
                  <SegmentId>af050469-b402-4255-b3c7-b0b0e3afc59c</SegmentId>
                  <MarkdownInternalBoldItem
                    internal_item_id="d38001bf-2d05-4bf6-8a3b-7246e03fac50"
                    internal_item_type="Bold">
                    <internal_items />
                    <internal_itatic_bold_item_type>Star</internal_itatic_bold_item_type>
                  </MarkdownInternalBoldItem>
                  <InternalNormalItem
                    internal_item_id="e0a60ac0-22ca-464a-bd79-5d06003ca955"
                    internal_item_type="Normal">
                    <internal_items />
                  </InternalNormalItem>
                </MarkdownSegment>
                <MarkdownSegment>
                  <SegmentId>52038e64-daf8-47f8-988c-f36aee651177</SegmentId>
                  <InternalNormalItem
                    internal_item_id="1ec12464-412f-4cbb-962c-b008ab31d770"
                    internal_item_type="Normal">
                    <internal_items />
                  </InternalNormalItem>
                </MarkdownSegment>
                <MarkdownSegment>
                  <SegmentId>e02865bb-c380-44b7-b1a8-e085fdd2889f</SegmentId>
                  <InternalNormalItem
                    internal_item_id="642e1e3e-13b6-4bd7-a75e-6db8b88054cc"
                    internal_item_type="Normal">
                    <internal_items />
                  </InternalNormalItem>
                </MarkdownSegment>
                <MarkdownSegment>
                  <SegmentId>56c1a98a-d110-4c03-b10f-9a4b74743ddf</SegmentId>
                  <InternalNormalItem
                    internal_item_id="1e468ae7-7e4f-4bd7-b850-292be0e004e0"
                    internal_item_type="Normal">
                    <internal_items />
                  </InternalNormalItem>
                </MarkdownSegment>
              </paragraph_segments>
            </MarkdownParagraphBlock>
            <Identifier>- </Identifier>
          </ListItem>
        </inner_list_items>
        <ListType>Charactor</ListType>
      </MarkdownBlockBase>
      <MarkdownBlockBase
        xsi:type="MarkdownHeaderBlock"
        item_id="a1f8cc6f-7642-41b5-9fae-9a0f95c7568f"
        item_type="Header"
        item_footer="footer_not_set">
        <header_type>Star</header_type>
        <header_level>2</header_level>
      </MarkdownBlockBase>
      <MarkdownBlockBase
        xsi:type="MarkdownParagraphBlock"
        item_id="cd0eba95-fabb-4015-bbf2-161f5f650e37"
        item_type="NormalParagraph"
        item_footer="">
        <paragraph_segments>
          <MarkdownSegment>
            <SegmentId>d6757b17-3fa6-4523-b612-6d25e74dc3df</SegmentId>
            <InternalNormalItem
              internal_item_id="f1d93001-f871-4bb4-86fd-ec1090d16160"
              internal_item_type="Normal">
              <internal_items />
            </InternalNormalItem>
          </MarkdownSegment>
        </paragraph_segments>
      </MarkdownBlockBase>
      <MarkdownBlockBase
        xsi:type="MarkdownParagraphBlock"
        item_id="99411839-56a4-477b-855e-ae30a85ac5bc"
        item_type="NormalParagraph"
        item_footer="&#xA;">
        <paragraph_segments>
          <MarkdownSegment>
            <SegmentId>3e0fc7e6-2560-4b5a-90b6-ca2491da50be</SegmentId>
            <InternalNormalItem
              internal_item_id="95ff0d99-5e1a-484f-b3e4-644f38b1c4c6"
              internal_item_type="Normal">
              <internal_items />
            </InternalNormalItem>
          </MarkdownSegment>
          <MarkdownSegment>
            <SegmentId>f4c4a779-f939-4316-be5e-aabc731bb55e</SegmentId>
            <InternalNormalItem
              internal_item_id="ddf15362-739d-44aa-b301-720b8dcbc9f5"
              internal_item_type="Normal">
              <internal_items />
            </InternalNormalItem>
          </MarkdownSegment>
        </paragraph_segments>
      </MarkdownBlockBase>
      <MarkdownBlockBase
        xsi:type="MarkdownHeaderBlock"
        item_id="353fa250-3186-4a25-aaf2-4e685690abb0"
        item_type="Header"
        item_footer="footer_not_set">
        <header_type>Star</header_type>
        <header_level>2</header_level>
      </MarkdownBlockBase>
      <MarkdownBlockBase
        xsi:type="MarkdownParagraphBlock"
        item_id="034a44eb-295a-46ce-9e9b-bd2b4858605b"
        item_type="NormalParagraph"
        item_footer="">
        <paragraph_segments>
          <MarkdownSegment>
            <SegmentId>42b94d02-8343-4ae5-b36e-039041bb92a5</SegmentId>
            <InternalNormalItem
              internal_item_id="4fbcd811-1b3f-409d-8708-5e145d5eaa48"
              internal_item_type="Normal">
              <internal_items />
            </InternalNormalItem>
          </MarkdownSegment>
          <MarkdownSegment>
            <SegmentId>f372433b-674b-4d5a-97fb-dfa1dc51cc3f</SegmentId>
            <InternalNormalItem
              internal_item_id="fb3b0a39-8dc9-4ffc-9b2f-109d97782d44"
              internal_item_type="Normal">
              <internal_items />
            </InternalNormalItem>
          </MarkdownSegment>
          <MarkdownSegment>
            <SegmentId>a425b3db-c26c-4067-a13f-7fcc801b1487</SegmentId>
            <InternalNormalItem
              internal_item_id="76584394-2958-4253-80d7-166ad974fc42"
              internal_item_type="Normal">
              <internal_items />
            </InternalNormalItem>
          </MarkdownSegment>
          <MarkdownSegment>
            <SegmentId>9dd2482f-cc49-4fb3-86cd-8eac5999e3f5</SegmentId>
            <InternalNormalItem
              internal_item_id="3b17da41-0d3b-48c6-b633-ea4ccda9d5d6"
              internal_item_type="Normal">
              <internal_items />
            </InternalNormalItem>
          </MarkdownSegment>
        </paragraph_segments>
      </MarkdownBlockBase>
      <MarkdownBlockBase
        xsi:type="MarkdownCodeBlock"
        item_id="8b87ec0b-ee9d-431b-b6b8-cc735a495970"
        item_type="CodeBlock"
        item_footer="footer_not_set">
        <code_block>Set-VMFirmware vmname -SecureBootTemplate MicrosoftUEFICertificateAuthority

</code_block>
      </MarkdownBlockBase>
      <MarkdownBlockBase
        xsi:type="MarkdownParagraphBlock"
        item_id="d2b26553-3e6e-4054-927f-b202e2182e71"
        item_type="NormalParagraph"
        item_footer="&#xA;">
        <paragraph_segments>
          <MarkdownSegment>
            <SegmentId>4f19649f-7e18-4480-92d9-5e391e3e4212</SegmentId>
            <InternalNormalItem
              internal_item_id="3b9ba70a-dc7e-4df7-96d5-b31bd527e1d8"
              internal_item_type="Normal">
              <internal_items />
            </InternalNormalItem>
            <LinkItem
              internal_item_id="a2643fa2-a2fd-461b-94b0-0505afe61aa2"
              internal_item_type="Link">
              <internal_items />
              <internal_link_type>Inline</internal_link_type>
              <internal_link_text>Linux and FreeBSD Virtual Machines on Hyper-V</internal_link_text>
              <internal_link_url>http://technet.microsoft.com/library/dn531030.aspx</internal_link_url>
              <internal_link_title />
            </LinkItem>
            <InternalNormalItem
              internal_item_id="98706648-3bf1-4b62-b98e-d0838d74e3c2"
              internal_item_type="Normal">
              <internal_items />
            </InternalNormalItem>
          </MarkdownSegment>
        </paragraph_segments>
      </MarkdownBlockBase>
      <MarkdownBlockBase
        xsi:type="MarkdownHeaderBlock"
        item_id="873e425b-cd40-45d6-8207-3f5c1d7a113b"
        item_type="Header"
        item_footer="footer_not_set">
        <header_type>Star</header_type>
        <header_level>2</header_level>
      </MarkdownBlockBase>
      <MarkdownBlockBase
        xsi:type="MarkdownParagraphBlock"
        item_id="dc80f05a-1709-4c07-ba99-125f0df4012c"
        item_type="NormalParagraph"
        item_footer="">
        <paragraph_segments>
          <MarkdownSegment>
            <SegmentId>4e099295-b408-4050-bda5-463bc55e0314</SegmentId>
            <InternalNormalItem
              internal_item_id="4a0ab236-19ce-45dd-b19f-85ab8d408779"
              internal_item_type="Normal">
              <internal_items />
            </InternalNormalItem>
          </MarkdownSegment>
          <MarkdownSegment>
            <SegmentId>6710d549-4f9f-455b-8a0a-147c0a4a8ac1</SegmentId>
            <InternalNormalItem
              internal_item_id="43f57623-b18e-4152-949f-07e5ab43bde2"
              internal_item_type="Normal">
              <internal_items />
            </InternalNormalItem>
          </MarkdownSegment>
          <MarkdownSegment>
            <SegmentId>d20ee95e-1751-40b0-88fa-49fa3f3bf4dc</SegmentId>
            <InternalNormalItem
              internal_item_id="bae34dd4-6148-436d-b4d3-b3376da27624"
              internal_item_type="Normal">
              <internal_items />
            </InternalNormalItem>
          </MarkdownSegment>
        </paragraph_segments>
      </MarkdownBlockBase>
      <MarkdownBlockBase
        xsi:type="MarkdownParagraphBlock"
        item_id="1c3f11e9-f2c2-4433-891f-948f6377ba9c"
        item_type="NormalParagraph"
        item_footer="">
        <paragraph_segments>
          <MarkdownSegment>
            <SegmentId>19541d4f-b850-4980-af4b-860f01317549</SegmentId>
            <InternalNormalItem
              internal_item_id="cb3ad30c-9c0e-4da3-9c39-50df3414274d"
              internal_item_type="Normal">
              <internal_items />
            </InternalNormalItem>
          </MarkdownSegment>
          <MarkdownSegment>
            <SegmentId>a0894228-9fa5-40ef-be64-d7a59c871fbb</SegmentId>
            <InternalNormalItem
              internal_item_id="b6c99d32-c6c4-4ef7-a8b8-838d2fe5c41d"
              internal_item_type="Normal">
              <internal_items />
            </InternalNormalItem>
          </MarkdownSegment>
          <MarkdownSegment>
            <SegmentId>931f72a5-852b-48b5-a4d9-6636161e34ee</SegmentId>
            <InternalNormalItem
              internal_item_id="4447cb7b-0c2f-4186-9d1f-8c7d20f56a43"
              internal_item_type="Normal">
              <internal_items />
            </InternalNormalItem>
          </MarkdownSegment>
        </paragraph_segments>
      </MarkdownBlockBase>
      <MarkdownBlockBase
        xsi:type="MarkdownHeaderBlock"
        item_id="2f8c66b9-02a9-48fb-b965-6202b6d0609f"
        item_type="Header"
        item_footer="footer_not_set">
        <header_type>Star</header_type>
        <header_level>4</header_level>
      </MarkdownBlockBase>
      <MarkdownBlockBase
        xsi:type="MarkdownParagraphBlock"
        item_id="5a014f53-7563-4a5a-a756-8839154eeb41"
        item_type="NormalParagraph"
        item_footer="">
        <paragraph_segments>
          <MarkdownSegment>
            <SegmentId>5fd5433d-8ec5-49be-932a-343289862e9b</SegmentId>
            <InternalNormalItem
              internal_item_id="63912a39-5b45-4f90-9c60-8e700ab354ff"
              internal_item_type="Normal">
              <internal_items />
            </InternalNormalItem>
          </MarkdownSegment>
        </paragraph_segments>
      </MarkdownBlockBase>
      <MarkdownBlockBase
        xsi:type="MarkdownFencedCodeBlock"
        item_id="23ea1e09-1c38-487f-bfcf-5a12804e670f"
        item_type="FencedCodeBlock"
        item_footer="">
        <codeblock_wraper>```</codeblock_wraper>
        <code_block>Get-VM * | Format-Table Name, Version</code_block>
        <fenced_code_lang> PowerShell</fenced_code_lang>
      </MarkdownBlockBase>
      <MarkdownBlockBase
        xsi:type="MarkdownHeaderBlock"
        item_id="921a9a63-693d-48c4-b18c-5a80e8a11b05"
        item_type="Header"
        item_footer="footer_not_set">
        <header_type>Star</header_type>
        <header_level>4</header_level>
      </MarkdownBlockBase>
      <MarkdownBlockBase
        xsi:type="MarkdownParagraphBlock"
        item_id="325ec5bd-4ae2-4d3c-b12c-8146e8de5499"
        item_type="NormalParagraph"
        item_footer="">
        <paragraph_segments>
          <MarkdownSegment>
            <SegmentId>6879f3e7-1ef6-4978-8dfb-122bdca0e0f3</SegmentId>
            <InternalNormalItem
              internal_item_id="b0534b07-873a-42bf-ae71-2c42b71458f8"
              internal_item_type="Normal">
              <internal_items />
            </InternalNormalItem>
          </MarkdownSegment>
        </paragraph_segments>
      </MarkdownBlockBase>
      <MarkdownBlockBase
        xsi:type="MarkdownFencedCodeBlock"
        item_id="147da5b6-d516-4877-bd78-944dbd99684d"
        item_type="FencedCodeBlock"
        item_footer="">
        <codeblock_wraper>```</codeblock_wraper>
        <code_block>Update-VmConfigurationVersion &lt;vmname&gt;</code_block>
        <fenced_code_lang> PowerShell</fenced_code_lang>
      </MarkdownBlockBase>
      <MarkdownBlockBase
        xsi:type="MarkdownParagraphBlock"
        item_id="c6a507d0-8e2e-44e5-a0f1-f139c2331130"
        item_type="NormalParagraph"
        item_footer="">
        <paragraph_segments>
          <MarkdownSegment>
            <SegmentId>5e867a32-9428-4f40-9b8c-a9690bc7a492</SegmentId>
            <InternalNormalItem
              internal_item_id="660d87b7-b116-41da-a1fc-6391b7d58a12"
              internal_item_type="Normal">
              <internal_items />
            </InternalNormalItem>
          </MarkdownSegment>
        </paragraph_segments>
      </MarkdownBlockBase>
      <MarkdownBlockBase
        xsi:type="MarkdownFencedCodeBlock"
        item_id="2ca08fa4-a02f-43f9-8886-5e68c209feb4"
        item_type="FencedCodeBlock"
        item_footer="&#xA;">
        <codeblock_wraper>```</codeblock_wraper>
        <code_block>Update-VmConfigurationVersion &lt;vmobject&gt;</code_block>
        <fenced_code_lang> PowerShell</fenced_code_lang>
      </MarkdownBlockBase>
      <MarkdownBlockBase
        xsi:type="MarkdownParagraphBlock"
        item_id="df193ef9-f59e-4b70-83a6-65c1c2ed1e55"
        item_type="NormalParagraph"
        item_footer="footer_not_set">
        <paragraph_segments>
          <MarkdownSegment>
            <SegmentId>3e4ef8d5-eaf4-4bd8-ac9b-97e232285b15</SegmentId>
            <ItalicsItem
              internal_item_id="2c0766e1-5044-46cd-92bc-97f621beb99e"
              internal_item_type="Italics">
              <internal_items />
              <internal_itatic_bold_item_type>Star</internal_itatic_bold_item_type>
            </ItalicsItem>
          </MarkdownSegment>
        </paragraph_segments>
      </MarkdownBlockBase>
      <MarkdownBlockBase
        xsi:type="MarkdownListBlock"
        item_id="4b60b312-8ed6-4a1e-9f85-ae3b8782e744"
        item_type="List"
        item_footer="&#xA;">
        <inner_list_items>
          <ListItem>
            <MarkdownParagraphBlock
              item_id="da125113-538a-46ed-9041-a36e6dc97425"
              item_type="NormalParagraph"
              item_footer="footer_not_set">
              <paragraph_segments>
                <MarkdownSegment>
                  <SegmentId>402188dc-27f9-44ff-a0bd-c76dd369a340</SegmentId>
                  <InternalNormalItem
                    internal_item_id="dde92c8d-a798-4160-976d-4f36b2988432"
                    internal_item_type="Normal">
                    <internal_items />
                  </InternalNormalItem>
                </MarkdownSegment>
              </paragraph_segments>
            </MarkdownParagraphBlock>
            <Identifier>- </Identifier>
          </ListItem>
          <ListItem>
            <MarkdownParagraphBlock
              item_id="d4d0bb6c-5e5f-48e9-893f-bb65840e40ed"
              item_type="NormalParagraph"
              item_footer="footer_not_set">
              <paragraph_segments>
                <MarkdownSegment>
                  <SegmentId>354bac16-a2dc-4247-8965-f7aaf9c61ea5</SegmentId>
                  <InternalNormalItem
                    internal_item_id="5963078c-0523-42f6-894b-e4a11bd93603"
                    internal_item_type="Normal">
                    <internal_items />
                  </InternalNormalItem>
                </MarkdownSegment>
              </paragraph_segments>
            </MarkdownParagraphBlock>
            <Identifier>- </Identifier>
          </ListItem>
          <ListItem>
            <MarkdownParagraphBlock
              item_id="e878fbf9-aa6e-40c5-96fc-3c81cabea61c"
              item_type="NormalParagraph"
              item_footer="footer_not_set">
              <paragraph_segments>
                <MarkdownSegment>
                  <SegmentId>a73787d9-23d5-4f5b-a490-27fda46a4bd6</SegmentId>
                  <InternalNormalItem
                    internal_item_id="16d98be0-4421-4e79-aea5-503572a53c20"
                    internal_item_type="Normal">
                    <internal_items />
                  </InternalNormalItem>
                </MarkdownSegment>
              </paragraph_segments>
            </MarkdownParagraphBlock>
            <Identifier>- </Identifier>
          </ListItem>
          <ListItem>
            <MarkdownParagraphBlock
              item_id="0cebe52d-04f6-4c57-a27b-86cf4c581b93"
              item_type="NormalParagraph"
              item_footer="footer_not_set">
              <paragraph_segments>
                <MarkdownSegment>
                  <SegmentId>40d094a3-723d-4d76-ab86-85ad539fa8b4</SegmentId>
                  <InternalNormalItem
                    internal_item_id="7db8aa9f-be07-45d4-9505-3229510f1876"
                    internal_item_type="Normal">
                    <internal_items />
                  </InternalNormalItem>
                </MarkdownSegment>
                <MarkdownSegment>
                  <SegmentId>a8bf856a-5415-49e8-906d-8f9ed0f9e8c8</SegmentId>
                  <InternalNormalItem
                    internal_item_id="8c79bf80-c48e-4360-aafc-fde0b4a9b641"
                    internal_item_type="Normal">
                    <internal_items />
                  </InternalNormalItem>
                </MarkdownSegment>
              </paragraph_segments>
            </MarkdownParagraphBlock>
            <Identifier>- </Identifier>
          </ListItem>
        </inner_list_items>
        <ListType>Charactor</ListType>
      </MarkdownBlockBase>
      <MarkdownBlockBase
        xsi:type="MarkdownHeaderBlock"
        item_id="ce0d1154-0556-42ed-bd9e-7a1f9af0a41b"
        item_type="Header"
        item_footer="footer_not_set">
        <header_type>Star</header_type>
        <header_level>2</header_level>
      </MarkdownBlockBase>
      <MarkdownBlockBase
        xsi:type="MarkdownParagraphBlock"
        item_id="fef5d61c-93b1-4c81-beef-fd018bb982a2"
        item_type="NormalParagraph"
        item_footer="&#xA;">
        <paragraph_segments>
          <MarkdownSegment>
            <SegmentId>affcaffd-3a76-42a8-91d3-926e2a44aed7</SegmentId>
            <InternalNormalItem
              internal_item_id="97e998da-6b4d-4bb8-94dd-ca12c527bd39"
              internal_item_type="Normal">
              <internal_items />
            </InternalNormalItem>
          </MarkdownSegment>
          <MarkdownSegment>
            <SegmentId>e5bb1469-fc80-4acf-8244-846dd5a2f352</SegmentId>
            <InternalNormalItem
              internal_item_id="e34095cd-edcf-464a-aa9a-d8bd60706036"
              internal_item_type="Normal">
              <internal_items />
            </InternalNormalItem>
          </MarkdownSegment>
          <MarkdownSegment>
            <SegmentId>11b4fd21-4f45-4ec5-bbc8-7cd7412f5298</SegmentId>
            <InternalNormalItem
              internal_item_id="8fbd6e09-39f9-4fcf-b96e-504fef4bb866"
              internal_item_type="Normal">
              <internal_items />
            </InternalNormalItem>
          </MarkdownSegment>
        </paragraph_segments>
      </MarkdownBlockBase>
      <MarkdownBlockBase
        xsi:type="MarkdownBlockQuote"
        item_id="95d2c704-7c16-4def-b19f-8adf01776615"
        item_type="BlockQuote"
        item_footer="&#xA;&#xA;">
        <MarkdownParagraphBlock
          item_id="40c7316f-d222-49e4-b2f2-c259da6b2c0a"
          item_type="NormalParagraph"
          item_footer="footer_not_set">
          <paragraph_segments>
            <MarkdownSegment>
              <SegmentId>585f7031-374e-4110-ad8d-dfb3ddc4108f</SegmentId>
              <MarkdownInternalBoldItem
                internal_item_id="82849ae6-5651-4d62-b9c4-78531c618331"
                internal_item_type="Bold">
                <internal_items />
                <internal_itatic_bold_item_type>Star</internal_itatic_bold_item_type>
              </MarkdownInternalBoldItem>
              <InternalNormalItem
                internal_item_id="4abeda36-0e9c-4040-b5ea-643031c3f45d"
                internal_item_type="Normal">
                <internal_items />
              </InternalNormalItem>
            </MarkdownSegment>
            <MarkdownSegment>
              <SegmentId>4329d05a-36fd-483d-991b-5a480652df5d</SegmentId>
              <InternalNormalItem
                internal_item_id="b9d4ab1b-4f93-4951-8f03-314396ef6a63"
                internal_item_type="Normal">
                <internal_items />
              </InternalNormalItem>
            </MarkdownSegment>
          </paragraph_segments>
        </MarkdownParagraphBlock>
      </MarkdownBlockBase>
      <MarkdownBlockBase
        xsi:type="MarkdownHeaderBlock"
        item_id="12bb72ee-837b-4c9c-828b-7194dda45f91"
        item_type="Header"
        item_footer="footer_not_set">
        <header_type>Star</header_type>
        <header_level>2</header_level>
      </MarkdownBlockBase>
      <MarkdownBlockBase
        xsi:type="MarkdownParagraphBlock"
        item_id="508550c5-3db9-460e-a89a-1fe99f107d80"
        item_type="NormalParagraph"
        item_footer="">
        <paragraph_segments>
          <MarkdownSegment>
            <SegmentId>3237718c-9afa-4da0-add7-11b446365219</SegmentId>
            <InternalNormalItem
              internal_item_id="4d0e0cc3-8a56-44a3-a7a5-274a52cf5343"
              internal_item_type="Normal">
              <internal_items />
            </InternalNormalItem>
          </MarkdownSegment>
        </paragraph_segments>
      </MarkdownBlockBase>
      <MarkdownBlockBase
        xsi:type="MarkdownParagraphBlock"
        item_id="8bcfec0e-7b19-4d21-877b-34404a5665ea"
        item_type="NormalParagraph"
        item_footer="&#xA;">
        <paragraph_segments>
          <MarkdownSegment>
            <SegmentId>4db7e111-2123-49f9-95cf-bb1575287744</SegmentId>
            <InternalNormalItem
              internal_item_id="09c4860f-14f1-4588-837f-b6526ae55853"
              internal_item_type="Normal">
              <internal_items />
            </InternalNormalItem>
          </MarkdownSegment>
          <MarkdownSegment>
            <SegmentId>8d005196-a1af-4cab-99f4-a22083abab44</SegmentId>
            <InternalNormalItem
              internal_item_id="bec36cb1-f5b8-481d-8d97-a8b04f882e85"
              internal_item_type="Normal">
              <internal_items />
            </InternalNormalItem>
          </MarkdownSegment>
          <MarkdownSegment>
            <SegmentId>81559c58-75b5-4e7c-a0a5-0367c5c8038a</SegmentId>
            <InternalNormalItem
              internal_item_id="900f4c9e-3289-4536-bfa3-3b209d6a66c0"
              internal_item_type="Normal">
              <internal_items />
            </InternalNormalItem>
          </MarkdownSegment>
        </paragraph_segments>
      </MarkdownBlockBase>
      <MarkdownBlockBase
        xsi:type="MarkdownParagraphBlock"
        item_id="aeb1b4fa-eb26-40e7-a57d-c6aec4690187"
        item_type="NormalParagraph"
        item_footer="　　&#xA;&#xA;">
        <paragraph_segments>
          <MarkdownSegment>
            <SegmentId>b492d1bc-600f-4450-8b5f-cf18096adcb2</SegmentId>
            <InternalNormalItem
              internal_item_id="6d441fb0-df9b-4e74-8277-153e9494649f"
              internal_item_type="Normal">
              <internal_items />
            </InternalNormalItem>
          </MarkdownSegment>
          <MarkdownSegment>
            <SegmentId>2d1d29f2-e332-49cf-9391-13afcd72cf23</SegmentId>
            <InternalNormalItem
              internal_item_id="54cf2d48-ea0b-45b1-94c8-2460f79e78d3"
              internal_item_type="Normal">
              <internal_items />
            </InternalNormalItem>
          </MarkdownSegment>
          <MarkdownSegment>
            <SegmentId>b224502d-fb31-4646-ac19-8b07aa72c3a5</SegmentId>
            <InternalNormalItem
              internal_item_id="3400710e-f600-4ad3-b7ba-027424704d42"
              internal_item_type="Normal">
              <internal_items />
            </InternalNormalItem>
          </MarkdownSegment>
          <MarkdownSegment>
            <SegmentId>98a55566-3e9d-4ceb-b2d7-148b3e531797</SegmentId>
            <InternalNormalItem
              internal_item_id="b17fde43-e5cc-49c5-94a2-c5f04b30cddf"
              internal_item_type="Normal">
              <internal_items />
            </InternalNormalItem>
          </MarkdownSegment>
          <MarkdownSegment>
            <SegmentId>0cff09b9-0dd3-4900-b1b7-f6059b3befed</SegmentId>
            <InternalNormalItem
              internal_item_id="662d1943-f160-47ed-9e5c-87327a929643"
              internal_item_type="Normal">
              <internal_items />
            </InternalNormalItem>
          </MarkdownSegment>
        </paragraph_segments>
      </MarkdownBlockBase>
      <MarkdownBlockBase
        xsi:type="MarkdownParagraphBlock"
        item_id="0a42519c-75bf-423b-a451-2c35687c408c"
        item_type="NormalParagraph"
        item_footer="&#xA;">
        <paragraph_segments>
          <MarkdownSegment>
            <SegmentId>7f78cf22-039b-47d5-a672-f215df794b91</SegmentId>
            <InternalNormalItem
              internal_item_id="adc1d668-eafd-48f8-84e6-49117f3d2373"
              internal_item_type="Normal">
              <internal_items />
            </InternalNormalItem>
          </MarkdownSegment>
        </paragraph_segments>
      </MarkdownBlockBase>
      <MarkdownBlockBase
        xsi:type="MarkdownParagraphBlock"
        item_id="493bc452-e7f6-46e0-b731-0a58fe7daeee"
        item_type="NormalParagraph"
        item_footer="footer_not_set">
        <paragraph_segments>
          <MarkdownSegment>
            <SegmentId>04f53d4e-23da-4c6a-ad86-cc526423bb8f</SegmentId>
            <InternalNormalItem
              internal_item_id="f1ac0414-e82d-411b-812f-eefd1c89946b"
              internal_item_type="Normal">
              <internal_items />
            </InternalNormalItem>
          </MarkdownSegment>
        </paragraph_segments>
      </MarkdownBlockBase>
      <MarkdownBlockBase
        xsi:type="MarkdownListBlock"
        item_id="e18a74e6-ac9c-4882-9680-df979e488904"
        item_type="List"
        item_footer="">
        <inner_list_items>
          <ListItem>
            <MarkdownParagraphBlock
              item_id="2305820b-a77d-4be3-8350-07640e5a503b"
              item_type="NormalParagraph"
              item_footer="footer_not_set">
              <paragraph_segments>
                <MarkdownSegment>
                  <SegmentId>6d2c76ee-c1cd-49e5-aa22-ee897610cfe6</SegmentId>
                  <InternalNormalItem
                    internal_item_id="b8a7d286-846c-4269-bf3a-1ac595b5a545"
                    internal_item_type="Normal">
                    <internal_items />
                  </InternalNormalItem>
                </MarkdownSegment>
              </paragraph_segments>
            </MarkdownParagraphBlock>
            <Identifier>*  </Identifier>
          </ListItem>
          <ListItem>
            <MarkdownParagraphBlock
              item_id="667e51b0-49e5-4233-aebf-5566cb589bb2"
              item_type="NormalParagraph"
              item_footer="footer_not_set">
              <paragraph_segments>
                <MarkdownSegment>
                  <SegmentId>b824ad50-776c-4a55-b670-2a932eff3e4b</SegmentId>
                  <InternalNormalItem
                    internal_item_id="a487d96d-a20d-4c9d-948c-e108a896e6ae"
                    internal_item_type="Normal">
                    <internal_items />
                  </InternalNormalItem>
                </MarkdownSegment>
              </paragraph_segments>
            </MarkdownParagraphBlock>
            <Identifier>*  </Identifier>
          </ListItem>
          <ListItem>
            <MarkdownParagraphBlock
              item_id="0ba72788-0b11-4c23-9e99-59a7cf37300e"
              item_type="NormalParagraph"
              item_footer="footer_not_set">
              <paragraph_segments>
                <MarkdownSegment>
                  <SegmentId>c6525be2-4ddd-4477-869e-a28eac843b63</SegmentId>
                  <InternalNormalItem
                    internal_item_id="f38a47b1-9447-44f3-bd20-fc781a941cf2"
                    internal_item_type="Normal">
                    <internal_items />
                  </InternalNormalItem>
                </MarkdownSegment>
              </paragraph_segments>
            </MarkdownParagraphBlock>
            <Identifier>*  </Identifier>
          </ListItem>
          <ListItem>
            <MarkdownParagraphBlock
              item_id="abef0bf5-cbf3-4615-9534-065caef1a02c"
              item_type="NormalParagraph"
              item_footer="footer_not_set">
              <paragraph_segments>
                <MarkdownSegment>
                  <SegmentId>53dae0ed-7793-49be-9adf-784224883943</SegmentId>
                  <InternalNormalItem
                    internal_item_id="6466ffe0-5f8e-4e0f-bb3e-8192ae2059a6"
                    internal_item_type="Normal">
                    <internal_items />
                  </InternalNormalItem>
                </MarkdownSegment>
              </paragraph_segments>
            </MarkdownParagraphBlock>
            <Identifier>*  </Identifier>
          </ListItem>
        </inner_list_items>
        <ListType>Charactor</ListType>
      </MarkdownBlockBase>
      <MarkdownBlockBase
        xsi:type="MarkdownParagraphBlock"
        item_id="783cabdc-a149-4852-aaf0-66b9f0da2fe8"
        item_type="NormalParagraph"
        item_footer="">
        <paragraph_segments>
          <MarkdownSegment>
            <SegmentId>1734be5a-941c-4879-b172-72d22afd5b80</SegmentId>
            <InternalNormalItem
              internal_item_id="4dcf0056-71ea-42e5-a980-8a6a50873e48"
              internal_item_type="Normal">
              <internal_items />
            </InternalNormalItem>
          </MarkdownSegment>
          <MarkdownSegment>
            <SegmentId>f587a1be-2028-47d7-8fe1-2422063a8982</SegmentId>
            <InternalNormalItem
              internal_item_id="a3728010-3c1a-4a41-8e11-60a3d1330360"
              internal_item_type="Normal">
              <internal_items />
            </InternalNormalItem>
          </MarkdownSegment>
        </paragraph_segments>
      </MarkdownBlockBase>
      <MarkdownBlockBase
        xsi:type="MarkdownParagraphBlock"
        item_id="9234d165-c943-475d-a7b1-8ec269c447a5"
        item_type="NormalParagraph"
        item_footer="&#xA;">
        <paragraph_segments>
          <MarkdownSegment>
            <SegmentId>c1a5286a-4144-4d88-a7fe-b06719d241bb</SegmentId>
            <InternalNormalItem
              internal_item_id="31ab17e3-4357-4d5e-9cff-dcf54175b2a4"
              internal_item_type="Normal">
              <internal_items />
            </InternalNormalItem>
            <LinkItem
              internal_item_id="070bdf94-7af7-49a3-b99b-027ffc061391"
              internal_item_type="Link">
              <internal_items />
              <internal_link_type>Inline</internal_link_type>
              <internal_link_text>blog post</internal_link_text>
              <internal_link_url>http://blogs.technet.com/b/virtualization/archive/2014/11/24/integration-components-how-we-determine-windows-update-applicability.aspx</internal_link_url>
              <internal_link_title />
            </LinkItem>
            <InternalNormalItem
              internal_item_id="b78838be-e007-4a40-a9fe-47c8510f47fe"
              internal_item_type="Normal">
              <internal_items />
            </InternalNormalItem>
          </MarkdownSegment>
        </paragraph_segments>
      </MarkdownBlockBase>
      <MarkdownBlockBase
        xsi:type="MarkdownParagraphBlock"
        item_id="978d2ad4-12e7-4a47-8f43-a75a814f5bc1"
        item_type="NormalParagraph"
        item_footer="&#xA;">
        <paragraph_segments>
          <MarkdownSegment>
            <SegmentId>3419885b-bff5-4f6e-bc10-16f87b02290f</SegmentId>
            <InternalNormalItem
              internal_item_id="ba7512f7-0128-4e98-8598-a2992905c17d"
              internal_item_type="Normal">
              <internal_items />
            </InternalNormalItem>
            <LinkItem
              internal_item_id="16e2bb5a-9c69-436d-b3a9-bbe1afa4ee47"
              internal_item_type="Link">
              <internal_items />
              <internal_link_type>Inline</internal_link_type>
              <internal_link_text>this blog</internal_link_text>
              <internal_link_url>http://blogs.msdn.com/b/virtual_pc_guy/archive/2014/11/12/updating-integration-components-over-windows-update.aspx</internal_link_url>
              <internal_link_title />
            </LinkItem>
            <InternalNormalItem
              internal_item_id="e5d81c41-f73c-4e01-939c-67958ee34062"
              internal_item_type="Normal">
              <internal_items />
            </InternalNormalItem>
          </MarkdownSegment>
        </paragraph_segments>
      </MarkdownBlockBase>
      <MarkdownBlockBase
        xsi:type="MarkdownBlockQuote"
        item_id="dec40196-936f-42e2-981f-49b1da8460bd"
        item_type="BlockQuote"
        item_footer="&#xA;&#xA;&#xA;">
        <MarkdownParagraphBlock
          item_id="7a5881cd-231f-4a85-9212-d0cde2341970"
          item_type="NormalParagraph"
          item_footer="footer_not_set">
          <paragraph_segments>
            <MarkdownSegment>
              <SegmentId>14140a39-ab98-40a7-a74d-5150097c8630</SegmentId>
              <MarkdownInternalBoldItem
                internal_item_id="b21762f0-cbf5-4400-a91e-0aa7b3d49efb"
                internal_item_type="Bold">
                <internal_items />
                <internal_itatic_bold_item_type>Star</internal_itatic_bold_item_type>
              </MarkdownInternalBoldItem>
              <InternalNormalItem
                internal_item_id="16a7ff8b-e21a-4a36-9e3e-0d5494df3fb3"
                internal_item_type="Normal">
                <internal_items />
              </InternalNormalItem>
            </MarkdownSegment>
            <MarkdownSegment>
              <SegmentId>ca049374-e6bf-4145-afd5-5c096c6ede96</SegmentId>
              <InternalNormalItem
                internal_item_id="8db5a9a3-607c-476b-a7e0-72b870fed8c7"
                internal_item_type="Normal">
                <internal_items />
              </InternalNormalItem>
            </MarkdownSegment>
          </paragraph_segments>
        </MarkdownParagraphBlock>
      </MarkdownBlockBase>
      <MarkdownBlockBase
        xsi:type="MarkdownHeaderBlock"
        item_id="f437f45f-16bb-4741-bb63-0425334db1e6"
        item_type="Header"
        item_footer="footer_not_set">
        <header_type>Star</header_type>
        <header_level>2</header_level>
      </MarkdownBlockBase>
      <MarkdownBlockBase
        xsi:type="MarkdownParagraphBlock"
        item_id="d3c26b6e-e1f8-437a-91d9-846470f1bec3"
        item_type="NormalParagraph"
        item_footer="&#xA;">
        <paragraph_segments>
          <MarkdownSegment>
            <SegmentId>c6e43781-3948-419c-9570-77c551a80dcf</SegmentId>
            <LinkItem
              internal_item_id="25344fe5-ea48-45c7-8cb6-27662435f35c"
              internal_item_type="Link">
              <internal_items />
              <internal_link_type>Inline</internal_link_type>
              <internal_link_text>Walk through Hyper-V on Windows 10</internal_link_text>
              <internal_link_url>..\quick_start\walkthrough.md</internal_link_url>
              <internal_link_title />
            </LinkItem>
          </MarkdownSegment>
        </paragraph_segments>
      </MarkdownBlockBase>
    </ArrayOfMarkdownBlockBase>
  </block_element>
  <references>
    <ArrayOfMarkdownLinkedReference xmlns:xsi="http://www.w3.org/2001/XMLSchema-instance" xmlns:xsd="http://www.w3.org/2001/XMLSchema" />
  </references>
</markdown_skeleton_root>s>
</markdown_skeleton_root>